Workbook

Sheet Dashboard
A1: Aros Media Dashboard
D8: Videos Produced | E8: Total Production Cost | F8: Total GMV | G8: Total Commission | H8: Total Profit | I8: ROI | J8: Total Orders | K8: Cost Per Order
D9: =COUNT('Video Database'!A:A) -> 1392 | E9: =sum('Video Database'!H:H) -> 635.9793 | F9: =SUM('Performance Data'!F:F) -> 1428.83 | G9: =SUM('Performance Data'!J:J) -> 200.639 | H9: =SUM('Performance Data'!S:S) -> -435.3403 | I9: =Dashboard!H9/Dashboard!E9 -> -0.68451961 | J9: =SUM('Performance Data'!G:G) -> 68 | K9: =E9/J9 -> 9.3526368

Sheet Management P&L
B2: Aros Media
B3: Management P&L Statement
B4: Revenue
B5: Direct Commissions | D5: =Dashboard!G9 -> 200.639
B6: Total Revenue | E6: =SUM(D5) -> 200.639
B8: Expenses
B9: Direct Production Expenses
B10: Creator Costs | C10: =-SUM('Video Database'!I2:I999) -> -578.163
B11: Editor Costs | C11: =-SUM('Video Database'!J2:J999) -> 0
B12: Platform Fees | C12: =-SUM('Video Database'!K2:K999) -> -57.8163
B13: Total Production Expenses | E13: =sum(C10:C12) -> -635.9793
B14: Gross Profit (Loss) | E14: =SUM(E6:E13) -> -435.3403
B15: Operating Expenses
B16: Account Costs | C16: =(-19.67-100-150-25-25-60) -> -379.67
B17: Failed Videos | C17: =-(66+16.5) -> -82.5
B18: Product Shipment | C18: -13.5
B19: Total Administrative Costs | D19: =SUM(C16:C18) -> -475.67
B20: Subscriptions
B21: Creator Hiring Platform Subscription | C21: =-(359.1+159.1) -> -518.2
B22: Editor Hiring Platform Subscription | C22: -69
B23: Google Workspace Subscription | C23: -4.01
B24: Domain Registration | C24: -12
B25: Total Subscription Costs | D25: =SUM(C21:C24) -> -603.21
B26: Product Sample Costs
B27: Goli Women's Complete Multi Gummy | C27: -5.6
B28: Medicube S.O.S Invisible Patch & Medicube No Cast Just Dew PDRN Sunscreen | C28: -32.16
B29: Jergens Natural Glow Hydra Gel Moisturizer | C29: -14.97
B30: Gruns Immun 13-in1 Immunity Gummies | C30: -8.99
B31: DR.DENT Purple Mouthwash | C31: -18.01
B32: Medicube Deoxyribose Scalp Serum | C32: -22.49
B33: Neuro Gum Watermlon Energy & Focus | C33: -26.49
B34: Taste Salud 2-in1 Skin & Beauty Drink Mix | C34: -21.99
B35: COSRX US AIRY LIGHT CLEAR SUNSCREEN STICK | C35: -21.45
B36: Bloom Nutrition Daily Hydration Sticks | C36: -9.99
B37: COSRX US Vitamin E Vitalizing Sunscreen | C37: -18.78
B38: COSRX US The Peptide Collagen Lifting Mask | C38: -11.69
... B42: TIRTIR Hydro UV Shield Sunscreen | C42: -12.23
B43: Total Product Sample Costs | D43: =SUM(C27:C42) -> -251.11
B44: Total Operating Expenses | E44: =SUM(D19:D43) -> -1329.99
B45: Total Operating Profit (Loss) | E45: =SUM(E14:E44) -> -1765.3303

Sheet Unit Economics
B2: Metric | C2: Calculation | D2: Result | E2: Interpretation
B3: Commission per Video | C3: Total Commission ÷ Videos | D3: =Dashboard!G9/Dashboard!D9 -> 0.14413721 | E3: Average video generates $0.14 in commission revenue
B4: Production Cost per Video | C4: Production Costs ÷ Videos | D4: =-Dashboard!E9/Dashboard!$D$9 -> -0.45688168 | E4: Average video costs $0.46 to produce
B5: Profit per Video | C5: Profit ÷ Videos | D5: =Dashboard!H9/Dashboard!$D$9 -> -0.31274447 | E5: Average video has a loss of $0.31
B6: Commission per Order | C6: Commission ÷ Orders | D6: =Dashboard!G9/Dashboard!$J$9 -> 2.9505735 | E6: Average order generates $2.95 in commission revenue
B7: Production Cost per Order | C7: Production Costs ÷ Orders | D7: =-Dashboard!E9/Dashboard!$J$9 -> -9.3526368 | E7: Average order has a $9.35 video production cost
B8: Profit per Order | C8: Profit ÷ Orders | D8: =Dashboard!H9/Dashboard!$J$9 -> -6.4020632 | E8: Average order has a loss of $6.40
B9: Overall ROI | C9: Total Profit ÷ Total Production Investment | D9: =Dashboard!H9/Dashboard!E9 -> -0.68451961 | E9: Aros Media lost $0.68 for every $1.00 invested into production costs
B10: Operating Margin | C10: Operating Profit (Loss) / Revenue | D10: ='Management P&L'!E45/Dashboard!G9 -> -8.7985402 | E10: Aros Media lost approximately $8.80 for every $1.00 of revenue after accounting for both production and operating expenses

Sheet Cost Structure
C2: Total Expenses | D2: =-'Management P&L'!E13+(-'Management P&L'!E44) -> 1965.9693
B4: Expense Category | C4: Expense | D4: Amount | E4: % of Total Expenses
B5: Production | C5: Creator Costs | D5: =SUM('Video Database'!I2:I1000) -> 578.163 | E5: =D5/D$2 -> 0.29408547
C6: Editor Costs | D6: 0 | E6: =D6/D$2 -> 0
C7: Platform Fees | D7: =SUM('Video Database'!K2:K1000) -> 57.8163 | E7: =D7/D$2 -> 0.029408547
B8: Total | D8: =SUM(D5:D7) -> 635.9793 | E8: =SUM(E5:E7) -> 0.32349401
B9: Operating | C9: Account Costs | D9: =-'Management P&L'!C16 -> 379.67 | E9: =D9/D$2 -> 0.19312102
C10: Failed Videos | D10: =-'Management P&L'!C17 -> 82.5 | E10: =D10/D$2 -> 0.041964033
C11: Product Shipment | D11: =-'Management P&L'!C18 -> 13.5 | E11: =D11/D$2 -> 0.0068668417
C12: Subscriptions | D12: =-'Management P&L'!D25 -> 603.21 | E12: =D12/D$2 -> 0.30682575
C13: Product Samples | D13: =-'Management P&L'!D43 -> 251.11 | E13: =D13/D$2 -> 0.12772834
B14: Total | D14: =SUM(D9:D13) -> 1329.99 | E14: =SUM(E9:E13) -> 0.67650599
B15: SUM | D15: =D14+D8 -> 1965.9693 | E15: =E14+E8 -> 1

Sheet Business Findings
A1: Aros Media Business Findings
B5: EXECUTIVE SUMMARY
B6: - Aros Media generated $200.64 in commission revenue against $1,965.97 in total expenses
B7: - Recorded an operating loss of $1,765.33
B8: - Subscriptions were the largest expense category, accounting for approximately 30.7% of total expenses
B9: - Profitability analysis identifies specifc products, creators, and content styles to investigate for future production decisions
B11: Prioritize high-performing products
B12: - Products such as JOYMODE Ignite Libido Support, IRIS Hormone Health Drink Mix, BetterAlt Shilajit Honey Sticks, tarte CC Color-Correct Tinted Serum, and Beast Bites Creatine Gummies generated the strongest profits and highest ROI.
B13: - Increase content production for these products based on their strong profit and ROI performance.
B15: Increase production for high-performing creators
B16: - Creators with consistently positive ROI should recieve a greater share of production resources.
B17: - Blakely was the only creator with positive ROI; prioritize additional production with this creator while monitoring performance.
B19: Reduce spending on underperforming content styles
... B34: - Reevaluating these subscriptions to reduce a major expense should be a top priority
C35: - Adjusting subscription tiers, switching to different platforms, etc.

Sheet Video Database
A1: Date Posted | B1: Month | C1: Week | D1: Creator | E1: Account | F1: Brand | G1: Product | H1: Total Cost: | I1: Creator Cost | J1: Editor Cost | K1: Platform Fee | L1: Video # | M1: Content Type
A2: 46179 | B2: =text(A2,"mmm yyyy") -> Jun 2026 | C2: =weeknum(A2) -> 23 | D2: Erin | E2: Account 4 | F2: Color Wow Hair | G2: Color Wow Quick Refresh and Styling Bundle | H2: =SUM(I2+J2+K2) -> 1.1 | I2: 1 | K2: =I2/10 -> 0.1 | L2: 1 | M2: Bottom of Funnel
A3: 46179 | B3: =text(A3,"mmm yyyy") -> Jun 2026 | C3: =weeknum(A3) -> 23 | D3: Erin | E3: Account 4 | F3: Color Wow Hair | G3: Color Wow Quick Refresh and Styling Bundle | H3: =SUM(I3+J3+K3) -> 1.1 | I3: 1 | K3: =I3/10 -> 0.1 | L3: =L2+1 -> 2 | M3: Bottom of Funnel
A4: 46179 | B4: =text(A4,"mmm yyyy") -> Jun 2026 | C4: =weeknum(A4) -> 23 | D4: Erin | E4: Account 4 | F4: Color Wow Hair | G4: Color Wow Quick Refresh and Styling Bundle | H4: =SUM(I4+J4+K4) -> 1.1 | I4: 1 | K4: =I4/10 -> 0.1 | L4: =L3+1 -> 3 | M4: Bottom of Funnel
A5: 46179 | B5: =text(A5,"mmm yyyy") -> Jun 2026 | C5: =weeknum(A5) -> 23 | D5: Erin | E5: Account 4 | F5: Color Wow Hair | G5: Color Wow Quick Refresh and Styling Bundle | H5: =SUM(I5+J5+K5) -> 1.1 | I5: 1 | K5: =I5/10 -> 0.1 | L5: =L4+1 -> 4 | M5: Bottom of Funnel
A6: 46179 | B6: =text(A6,"mmm yyyy") -> Jun 2026 | C6: =weeknum(A6) -> 23 | D6: Erin | E6: Account 4 | F6: Color Wow Hair | G6: Color Wow Quick Refresh and Styling Bundle | H6: =SUM(I6+J6+K6) -> 1.1 | I6: 1 | K6: =I6/10 -> 0.1 | L6: =L5+1 -> 5 | M6: Bottom of Funnel
A7: 46179 | B7: =text(A7,"mmm yyyy") -> Jun 2026 | C7: =weeknum(A7) -> 23 | D7: Erin | E7: Account 4 | F7: Color Wow Hair | G7: Color Wow Quick Refresh and Styling Bundle | H7: =SUM(I7+J7+K7) -> 1.1 | I7: 1 | K7: =I7/10 -> 0.1 | L7: =L6+1 -> 6 | M7: Bottom of Funnel
A8: 46179 | B8: =text(A8,"mmm yyyy") -> Jun 2026 | C8: =weeknum(A8) -> 23 | D8: Erin | E8: Account 4 | F8: Color Wow Hair | G8: Color Wow Quick Refresh and Styling Bundle | H8: =SUM(I8+J8+K8) -> 1.1 | I8: 1 | K8: =I8/10 -> 0.1 | L8: =L7+1 -> 7 | M8: Bottom of Funnel
A9: 46179 | B9: =text(A9,"mmm yyyy") -> Jun 2026 | C9: =weeknum(A9) -> 23 | D9: Erin | E9: Account 4 | F9: Color Wow Hair | G9: Color Wow Quick Refresh and Styling Bundle | H9: =SUM(I9+J9+K9) -> 1.1 | I9: 1 | K9: =I9/10 -> 0.1 | L9: =L8+1 -> 8 | M9: Bottom of Funnel
A10: 46179 | B10: =text(A10,"mmm yyyy") -> Jun 2026 | C10: =weeknum(A10) -> 23 | D10: Erin | E10: Account 4 | F10: Color Wow Hair | G10: Color Wow Quick Refresh and Styling Bundle | H10: =SUM(I10+J10+K10) -> 1.1 | I10: 1 | K10: =I10/10 -> 0.1 | L10: =L9+1 -> 9 | M10: Bottom of Funnel
A11: 46179 | B11: =text(A11,"mmm yyyy") -> Jun 2026 | C11: =weeknum(A11) -> 23 | D11: Erin | E11: Account 4 | F11: Color Wow Hair | G11: Color Wow Quick Refresh and Styling Bundle | H11: =SUM(I11+J11+K11) -> 1.1 | I11: 1 | K11: =I11/10 -> 0.1 | L11: =L10+1 -> 10 | M11: Bottom of Funnel
A12: 46179 | B12: =text(A12,"mmm yyyy") -> Jun 2026 | C12: =weeknum(A12) -> 23 | D12: Erin | E12: Account 4 | F12: Color Wow Hair | G12: Color Wow Quick Refresh and Styling Bundle | H12: =SUM(I12+J12+K12) -> 1.1 | I12: 1 | K12: =I12/10 -> 0.1 | L12: =L11+1 -> 11 | M12: Bottom of Funnel
A13: 46179 | B13: =text(A13,"mmm yyyy") -> Jun 2026 | C13: =weeknum(A13) -> 23 | D13: Erin | E13: Account 4 | F13: Color Wow Hair | G13: Color Wow Quick Refresh and Styling Bundle | H13: =SUM(I13+J13+K13) -> 1.1 | I13: 1 | K13: =I13/10 -> 0.1 | L13: =L12+1 -> 12 | M13: Bottom of Funnel
A14: 46179 | B14: =text(A14,"mmm yyyy") -> Jun 2026 | C14: =weeknum(A14) -> 23 | D14: Erin | E14: Account 4 | F14: Color Wow Hair | G14: Color Wow Quick Refresh and Styling Bundle | H14: =SUM(I14+J14+K14) -> 1.1 | I14: 1 | K14: =I14/10 -> 0.1 | L14: =L13+1 -> 13 | M14: Bottom of Funnel
... A1393: 46208 | B1393: =text(A1393,"mmm yyyy") -> Jul 2026 | C1393: =weeknum(A1393) -> 28 | D1393: Brittney | E1393: Account 4 | F1393: Gruns | G1393: Gruns Greens Popsicle Firecracker Gummies | H1393: =SUM(I1393+J1393+K1393) -> 0.11 | I1393: 0.1 | K1393: =I1393/10 -> 0.01 | L1393: =L1392+1 -> 1392 | M1393: Bottom of Funnel

Sheet Performance Data
A1: Video # | B1: Creator | C1: Account | D1: Product | E1: Total Cost | F1: GMV | G1: Orders | H1: Date Posted | I1: Date Updated | J1: Commission | K1: Clicks | L1: Impressions | M1: Views | N1: Avg Watch Time | O1: CTR | P1: CTOR | Q1: Comimission per Order | R1: GMV per Order | S1: Profit | T1: ROI | U1: Profit Margin | V1: Cost per Order | W1: Cost per Click | X1: Cost Per $100 GMV | Y1: Content Style
A2: 1 | B2: {=_xlfn.XLOOKUP(A2,'Video Database'!L:L,'Video Database'!D:D,"")} -> Erin | C2: {=_xlfn.XLOOKUP(A2,'Video Database'!L:L,'Video Database'!E:E,"")} -> Account 4 | D2: {=_xlfn.XLOOKUP(A2,'Video Database'!L:L,'Video Database'!G:G,"")} -> Color Wow Quick Refresh and Styling Bundle | E2: {=_xlfn.XLOOKUP(A2,'Video Database'!L:L,'Video Database'!H:H,"")} -> 1.1 | F2: 0 | G2: 0 | H2: {=_xlfn.XLOOKUP(A2,'Video Database'!L:L,'Video Database'!A:A,"")} -> 46179 | I2: 46201 | J2: 0 | L2: =M2 | O2: =iferror(K2/L2, NA()) -> #N/A | P2: =iferror(G2/K2, NA()) -> #N/A | Q2: =iferror(J2/G2,NA()) -> #N/A | R2: =iferror(F2/G2,NA()) -> #N/A | S2: =J2-E2 -> -1.1 | T2: =if(E2=0,"",S2/E2) -> -1 | U2: =iferror(S2/J2,na()) -> #N/A | V2: =if(G2=0,"",E2/G2) | W2: =if(K2=0,"",E2/K2) | X2: =if(F2=0,"",(E2/F2)*100) | Y2: {=_xlfn.XLOOKUP(A2,'Video Database'!L:L,'Video Database'!M:M,"")} -> Bottom of Funnel
A3: =A2+1 -> 2 | B3: {=_xlfn.XLOOKUP(A3,'Video Database'!L:L,'Video Database'!D:D,"")} -> Erin | C3: {=_xlfn.XLOOKUP(A3,'Video Database'!L:L,'Video Database'!E:E,"")} -> Account 4 | D3: {=_xlfn.XLOOKUP(A3,'Video Database'!L:L,'Video Database'!G:G,"")} -> Color Wow Quick Refresh and Styling Bundle | E3: {=_xlfn.XLOOKUP(A3,'Video Database'!L:L,'Video Database'!H:H,"")} -> 1.1 | F3: 0 | G3: 0 | H3: {=_xlfn.XLOOKUP(A3,'Video Database'!L:L,'Video Database'!A:A,"")} -> 46179 | I3: 46201 | J3: 0 | L3: =M3 | O3: =iferror(K3/L3, NA()) -> #N/A | P3: =iferror(G3/K3, NA()) -> #N/A | Q3: =iferror(J3/G3,NA()) -> #N/A | R3: =iferror(F3/G3,NA()) -> #N/A | S3: =J3-E3 -> -1.1 | T3: =if(E3=0,"",S3/E3) -> -1 | U3: =iferror(S3/J3,na()) -> #N/A | V3: =if(G3=0,"",E3/G3) | W3: =if(K3=0,"",E3/K3) | X3: =if(F3=0,"",(E3/F3)*100) | Y3: {=_xlfn.XLOOKUP(A3,'Video Database'!L:L,'Video Database'!M:M,"")} -> Bottom of Funnel
A4: =A3+1 -> 3 | B4: {=_xlfn.XLOOKUP(A4,'Video Database'!L:L,'Video Database'!D:D,"")} -> Erin | C4: {=_xlfn.XLOOKUP(A4,'Video Database'!L:L,'Video Database'!E:E,"")} -> Account 4 | D4: {=_xlfn.XLOOKUP(A4,'Video Database'!L:L,'Video Database'!G:G,"")} -> Color Wow Quick Refresh and Styling Bundle | E4: {=_xlfn.XLOOKUP(A4,'Video Database'!L:L,'Video Database'!H:H,"")} -> 1.1 | F4: 0 | G4: 0 | H4: {=_xlfn.XLOOKUP(A4,'Video Database'!L:L,'Video Database'!A:A,"")} -> 46179 | I4: 46201 | J4: 0 | L4: =M4 | O4: =iferror(K4/L4, NA()) -> #N/A | P4: =iferror(G4/K4, NA()) -> #N/A | Q4: =iferror(J4/G4,NA()) -> #N/A | R4: =iferror(F4/G4,NA()) -> #N/A | S4: =J4-E4 -> -1.1 | T4: =if(E4=0,"",S4/E4) -> -1 | U4: =iferror(S4/J4,na()) -> #N/A | V4: =if(G4=0,"",E4/G4) | W4: =if(K4=0,"",E4/K4) | X4: =if(F4=0,"",(E4/F4)*100) | Y4: {=_xlfn.XLOOKUP(A4,'Video Database'!L:L,'Video Database'!M:M,"")} -> Bottom of Funnel
A5: =A4+1 -> 4 | B5: {=_xlfn.XLOOKUP(A5,'Video Database'!L:L,'Video Database'!D:D,"")} -> Erin | C5: {=_xlfn.XLOOKUP(A5,'Video Database'!L:L,'Video Database'!E:E,"")} -> Account 4 | D5: {=_xlfn.XLOOKUP(A5,'Video Database'!L:L,'Video Database'!G:G,"")} -> Color Wow Quick Refresh and Styling Bundle | E5: {=_xlfn.XLOOKUP(A5,'Video Database'!L:L,'Video Database'!H:H,"")} -> 1.1 | F5: 0 | G5: 0 | H5: {=_xlfn.XLOOKUP(A5,'Video Database'!L:L,'Video Database'!A:A,"")} -> 46179 | I5: 46201 | J5: 0 | L5: =M5 | O5: =iferror(K5/L5, NA()) -> #N/A | P5: =iferror(G5/K5, NA()) -> #N/A | Q5: =iferror(J5/G5,NA()) -> #N/A | R5: =iferror(F5/G5,NA()) -> #N/A | S5: =J5-E5 -> -1.1 | T5: =if(E5=0,"",S5/E5) -> -1 | U5: =iferror(S5/J5,na()) -> #N/A | V5: =if(G5=0,"",E5/G5) | W5: =if(K5=0,"",E5/K5) | X5: =if(F5=0,"",(E5/F5)*100) | Y5: {=_xlfn.XLOOKUP(A5,'Video Database'!L:L,'Video Database'!M:M,"")} -> Bottom of Funnel
A6: =A5+1 -> 5 | B6: {=_xlfn.XLOOKUP(A6,'Video Database'!L:L,'Video Database'!D:D,"")} -> Erin | C6: {=_xlfn.XLOOKUP(A6,'Video Database'!L:L,'Video Database'!E:E,"")} -> Account 4 | D6: {=_xlfn.XLOOKUP(A6,'Video Database'!L:L,'Video Database'!G:G,"")} -> Color Wow Quick Refresh and Styling Bundle | E6: {=_xlfn.XLOOKUP(A6,'Video Database'!L:L,'Video Database'!H:H,"")} -> 1.1 | F6: 0 | G6: 0 | H6: {=_xlfn.XLOOKUP(A6,'Video Database'!L:L,'Video Database'!A:A,"")} -> 46179 | I6: 46201 | J6: 0 | L6: =M6 | O6: =iferror(K6/L6, NA()) -> #N/A | P6: =iferror(G6/K6, NA()) -> #N/A | Q6: =iferror(J6/G6,NA()) -> #N/A | R6: =iferror(F6/G6,NA()) -> #N/A | S6: =J6-E6 -> -1.1 | T6: =if(E6=0,"",S6/E6) -> -1 | U6: =iferror(S6/J6,na()) -> #N/A | V6: =if(G6=0,"",E6/G6) | W6: =if(K6=0,"",E6/K6) | X6: =if(F6=0,"",(E6/F6)*100) | Y6: {=_xlfn.XLOOKUP(A6,'Video Database'!L:L,'Video Database'!M:M,"")} -> Bottom of Funnel
A7: =A6+1 -> 6 | B7: {=_xlfn.XLOOKUP(A7,'Video Database'!L:L,'Video Database'!D:D,"")} -> Erin | C7: {=_xlfn.XLOOKUP(A7,'Video Database'!L:L,'Video Database'!E:E,"")} -> Account 4 | D7: {=_xlfn.XLOOKUP(A7,'Video Database'!L:L,'Video Database'!G:G,"")} -> Color Wow Quick Refresh and Styling Bundle | E7: {=_xlfn.XLOOKUP(A7,'Video Database'!L:L,'Video Database'!H:H,"")} -> 1.1 | F7: 0 | G7: 0 | H7: {=_xlfn.XLOOKUP(A7,'Video Database'!L:L,'Video Database'!A:A,"")} -> 46179 | I7: 46201 | J7: 0 | L7: =M7 | O7: =iferror(K7/L7, NA()) -> #N/A | P7: =iferror(G7/K7, NA()) -> #N/A | Q7: =iferror(J7/G7,NA()) -> #N/A | R7: =iferror(F7/G7,NA()) -> #N/A | S7: =J7-E7 -> -1.1 | T7: =if(E7=0,"",S7/E7) -> -1 | U7: =iferror(S7/J7,na()) -> #N/A | V7: =if(G7=0,"",E7/G7) | W7: =if(K7=0,"",E7/K7) | X7: =if(F7=0,"",(E7/F7)*100) | Y7: {=_xlfn.XLOOKUP(A7,'Video Database'!L:L,'Video Database'!M:M,"")} -> Bottom of Funnel
A8: =A7+1 -> 7 | B8: {=_xlfn.XLOOKUP(A8,'Video Database'!L:L,'Video Database'!D:D,"")} -> Erin | C8: {=_xlfn.XLOOKUP(A8,'Video Database'!L:L,'Video Database'!E:E,"")} -> Account 4 | D8: {=_xlfn.XLOOKUP(A8,'Video Database'!L:L,'Video Database'!G:G,"")} -> Color Wow Quick Refresh and Styling Bundle | E8: {=_xlfn.XLOOKUP(A8,'Video Database'!L:L,'Video Database'!H:H,"")} -> 1.1 | F8: 0 | G8: 0 | H8: {=_xlfn.XLOOKUP(A8,'Video Database'!L:L,'Video Database'!A:A,"")} -> 46179 | I8: 46201 | J8: 0 | L8: =M8 | O8: =iferror(K8/L8, NA()) -> #N/A | P8: =iferror(G8/K8, NA()) -> #N/A | Q8: =iferror(J8/G8,NA()) -> #N/A | R8: =iferror(F8/G8,NA()) -> #N/A | S8: =J8-E8 -> -1.1 | T8: =if(E8=0,"",S8/E8) -> -1 | U8: =iferror(S8/J8,na()) -> #N/A | V8: =if(G8=0,"",E8/G8) | W8: =if(K8=0,"",E8/K8) | X8: =if(F8=0,"",(E8/F8)*100) | Y8: {=_xlfn.XLOOKUP(A8,'Video Database'!L:L,'Video Database'!M:M,"")} -> Bottom of Funnel
A9: =A8+1 -> 8 | B9: {=_xlfn.XLOOKUP(A9,'Video Database'!L:L,'Video Database'!D:D,"")} -> Erin | C9: {=_xlfn.XLOOKUP(A9,'Video Database'!L:L,'Video Database'!E:E,"")} -> Account 4 | D9: {=_xlfn.XLOOKUP(A9,'Video Database'!L:L,'Video Database'!G:G,"")} -> Color Wow Quick Refresh and Styling Bundle | E9: {=_xlfn.XLOOKUP(A9,'Video Database'!L:L,'Video Database'!H:H,"")} -> 1.1 | F9: 0 | G9: 0 | H9: {=_xlfn.XLOOKUP(A9,'Video Database'!L:L,'Video Database'!A:A,"")} -> 46179 | I9: 46201 | J9: 0 | L9: =M9 | O9: =iferror(K9/L9, NA()) -> #N/A | P9: =iferror(G9/K9, NA()) -> #N/A | Q9: =iferror(J9/G9,NA()) -> #N/A | R9: =iferror(F9/G9,NA()) -> #N/A | S9: =J9-E9 -> -1.1 | T9: =if(E9=0,"",S9/E9) -> -1 | U9: =iferror(S9/J9,na()) -> #N/A | V9: =if(G9=0,"",E9/G9) | W9: =if(K9=0,"",E9/K9) | X9: =if(F9=0,"",(E9/F9)*100) | Y9: {=_xlfn.XLOOKUP(A9,'Video Database'!L:L,'Video Database'!M:M,"")} -> Bottom of Funnel
A10: =A9+1 -> 9 | B10: {=_xlfn.XLOOKUP(A10,'Video Database'!L:L,'Video Database'!D:D,"")} -> Erin | C10: {=_xlfn.XLOOKUP(A10,'Video Database'!L:L,'Video Database'!E:E,"")} -> Account 4 | D10: {=_xlfn.XLOOKUP(A10,'Video Database'!L:L,'Video Database'!G:G,"")} -> Color Wow Quick Refresh and Styling Bundle | E10: {=_xlfn.XLOOKUP(A10,'Video Database'!L:L,'Video Database'!H:H,"")} -> 1.1 | F10: 0 | G10: 0 | H10: {=_xlfn.XLOOKUP(A10,'Video Database'!L:L,'Video Database'!A:A,"")} -> 46179 | I10: 46201 | J10: 0 | L10: =M10 | O10: =iferror(K10/L10, NA()) -> #N/A | P10: =iferror(G10/K10, NA()) -> #N/A | Q10: =iferror(J10/G10,NA()) -> #N/A | R10: =iferror(F10/G10,NA()) -> #N/A | S10: =J10-E10 -> -1.1 | T10: =if(E10=0,"",S10/E10) -> -1 | U10: =iferror(S10/J10,na()) -> #N/A | V10: =if(G10=0,"",E10/G10) | W10: =if(K10=0,"",E10/K10) | X10: =if(F10=0,"",(E10/F10)*100) | Y10: {=_xlfn.XLOOKUP(A10,'Video Database'!L:L,'Video Database'!M:M,"")} -> Bottom of Funnel
A11: =A10+1 -> 10 | B11: {=_xlfn.XLOOKUP(A11,'Video Database'!L:L,'Video Database'!D:D,"")} -> Erin | C11: {=_xlfn.XLOOKUP(A11,'Video Database'!L:L,'Video Database'!E:E,"")} -> Account 4 | D11: {=_xlfn.XLOOKUP(A11,'Video Database'!L:L,'Video Database'!G:G,"")} -> Color Wow Quick Refresh and Styling Bundle | E11: {=_xlfn.XLOOKUP(A11,'Video Database'!L:L,'Video Database'!H:H,"")} -> 1.1 | F11: 0 | G11: 0 | H11: {=_xlfn.XLOOKUP(A11,'Video Database'!L:L,'Video Database'!A:A,"")} -> 46179 | I11: 46201 | J11: 0 | L11: =M11 | O11: =iferror(K11/L11, NA()) -> #N/A | P11: =iferror(G11/K11, NA()) -> #N/A | Q11: =iferror(J11/G11,NA()) -> #N/A | R11: =iferror(F11/G11,NA()) -> #N/A | S11: =J11-E11 -> -1.1 | T11: =if(E11=0,"",S11/E11) -> -1 | U11: =iferror(S11/J11,na()) -> #N/A | V11: =if(G11=0,"",E11/G11) | W11: =if(K11=0,"",E11/K11) | X11: =if(F11=0,"",(E11/F11)*100) | Y11: {=_xlfn.XLOOKUP(A11,'Video Database'!L:L,'Video Database'!M:M,"")} -> Bottom of Funnel
A12: =A11+1 -> 11 | B12: {=_xlfn.XLOOKUP(A12,'Video Database'!L:L,'Video Database'!D:D,"")} -> Erin | C12: {=_xlfn.XLOOKUP(A12,'Video Database'!L:L,'Video Database'!E:E,"")} -> Account 4 | D12: {=_xlfn.XLOOKUP(A12,'Video Database'!L:L,'Video Database'!G:G,"")} -> Color Wow Quick Refresh and Styling Bundle | E12: {=_xlfn.XLOOKUP(A12,'Video Database'!L:L,'Video Database'!H:H,"")} -> 1.1 | F12: 0 | G12: 0 | H12: {=_xlfn.XLOOKUP(A12,'Video Database'!L:L,'Video Database'!A:A,"")} -> 46179 | I12: 46201 | J12: 0 | L12: =M12 | O12: =iferror(K12/L12, NA()) -> #N/A | P12: =iferror(G12/K12, NA()) -> #N/A | Q12: =iferror(J12/G12,NA()) -> #N/A | R12: =iferror(F12/G12,NA()) -> #N/A | S12: =J12-E12 -> -1.1 | T12: =if(E12=0,"",S12/E12) -> -1 | U12: =iferror(S12/J12,na()) -> #N/A | V12: =if(G12=0,"",E12/G12) | W12: =if(K12=0,"",E12/K12) | X12: =if(F12=0,"",(E12/F12)*100) | Y12: {=_xlfn.XLOOKUP(A12,'Video Database'!L:L,'Video Database'!M:M,"")} -> Bottom of Funnel
A13: =A12+1 -> 12 | B13: {=_xlfn.XLOOKUP(A13,'Video Database'!L:L,'Video Database'!D:D,"")} -> Erin | C13: {=_xlfn.XLOOKUP(A13,'Video Database'!L:L,'Video Database'!E:E,"")} -> Account 4 | D13: {=_xlfn.XLOOKUP(A13,'Video Database'!L:L,'Video Database'!G:G,"")} -> Color Wow Quick Refresh and Styling Bundle | E13: {=_xlfn.XLOOKUP(A13,'Video Database'!L:L,'Video Database'!H:H,"")} -> 1.1 | F13: 0 | G13: 0 | H13: {=_xlfn.XLOOKUP(A13,'Video Database'!L:L,'Video Database'!A:A,"")} -> 46179 | I13: 46201 | J13: 0 | L13: =M13 | O13: =iferror(K13/L13, NA()) -> #N/A | P13: =iferror(G13/K13, NA()) -> #N/A | Q13: =iferror(J13/G13,NA()) -> #N/A | R13: =iferror(F13/G13,NA()) -> #N/A | S13: =J13-E13 -> -1.1 | T13: =if(E13=0,"",S13/E13) -> -1 | U13: =iferror(S13/J13,na()) -> #N/A | V13: =if(G13=0,"",E13/G13) | W13: =if(K13=0,"",E13/K13) | X13: =if(F13=0,"",(E13/F13)*100) | Y13: {=_xlfn.XLOOKUP(A13,'Video Database'!L:L,'Video Database'!M:M,"")} -> Bottom of Funnel
A14: =A13+1 -> 13 | B14: {=_xlfn.XLOOKUP(A14,'Video Database'!L:L,'Video Database'!D:D,"")} -> Erin | C14: {=_xlfn.XLOOKUP(A14,'Video Database'!L:L,'Video Database'!E:E,"")} -> Account 4 | D14: {=_xlfn.XLOOKUP(A14,'Video Database'!L:L,'Video Database'!G:G,"")} -> Color Wow Quick Refresh and Styling Bundle | E14: {=_xlfn.XLOOKUP(A14,'Video Database'!L:L,'Video Database'!H:H,"")} -> 1.1 | F14: 0 | G14: 0 | H14: {=_xlfn.XLOOKUP(A14,'Video Database'!L:L,'Video Database'!A:A,"")} -> 46179 | I14: 46201 | J14: 0 | L14: =M14 | O14: =iferror(K14/L14, NA()) -> #N/A | P14: =iferror(G14/K14, NA()) -> #N/A | Q14: =iferror(J14/G14,NA()) -> #N/A | R14: =iferror(F14/G14,NA()) -> #N/A | S14: =J14-E14 -> -1.1 | T14: =if(E14=0,"",S14/E14) -> -1 | U14: =iferror(S14/J14,na()) -> #N/A | V14: =if(G14=0,"",E14/G14) | W14: =if(K14=0,"",E14/K14) | X14: =if(F14=0,"",(E14/F14)*100) | Y14: {=_xlfn.XLOOKUP(A14,'Video Database'!L:L,'Video Database'!M:M,"")} -> Bottom of Funnel
... A46: =A45+1 -> 45 | B46: {=_xlfn.XLOOKUP(A46,'Video Database'!L:L,'Video Database'!D:D,"")} -> Erin | C46: {=_xlfn.XLOOKUP(A46,'Video Database'!L:L,'Video Database'!E:E,"")} -> Account 4 | D46: {=_xlfn.XLOOKUP(A46,'Video Database'!L:L,'Video Database'!G:G,"")} -> Stainless Steel Gua Sha | E46: {=_xlfn.XLOOKUP(A46,'Video Database'!L:L,'Video Database'!H:H,"")} -> 1.1 | F46: 0 | G46: 0 | H46: {=_xlfn.XLOOKUP(A46,'Video Database'!L:L,'Video Database'!A:A,"")} -> 46181 | I46: 46201 | J46: 0 | L46: =M46 | O46: =iferror(K46/L46, NA()) -> #N/A | P46: =iferror(G46/K46, NA()) -> #N/A | Q46: =iferror(J46/G46,NA()) -> #N/A | R46: =iferror(F46/G46,NA()) -> #N/A | S46: =J46-E46 -> -1.1 | T46: =if(E46=0,"",S46/E46) -> -1 | U46: =iferror(S46/J46,na()) -> #N/A | V46: =if(G46=0,"",E46/G46) | W46: =if(K46=0,"",E46/K46) | X46: =if(F46=0,"",(E46/F46)*100) | Y46: {=_xlfn.XLOOKUP(A46,'Video Database'!L:L,'Video Database'!M:M,"")} -> Bottom of Funnel
A47: =A46+1 -> 46 | B47: {=_xlfn.XLOOKUP(A47,'Video Database'!L:L,'Video Database'!D:D,"")} -> Erin | C47: {=_xlfn.XLOOKUP(A47,'Video Database'!L:L,'Video Database'!E:E,"")} -> Account 4 | D47: {=_xlfn.XLOOKUP(A47,'Video Database'!L:L,'Video Database'!G:G,"")} -> Stainless Steel Gua Sha | E47: {=_xlfn.XLOOKUP(A47,'Video Database'!L:L,'Video Database'!H:H,"")} -> 1.1 | F47: 17.16 | G47: 1 | H47: {=_xlfn.XLOOKUP(A47,'Video Database'!L:L,'Video Database'!A:A,"")} -> 46181 | I47: 46201 | J47: 1.04 | K47: 3 | L47: =M47 -> 100 | M47: 100 | O47: =iferror(K47/L47, NA()) -> 0.03 | P47: =iferror(G47/K47, NA()) -> 0.33333333 | Q47: =iferror(J47/G47,NA()) -> 1.04 | R47: =iferror(F47/G47,NA()) -> 17.16 | S47: =J47-E47 -> -0.06 | T47: =if(E47=0,"",S47/E47) -> -0.054545455 | U47: =iferror(S47/J47,na()) -> -0.057692308 | V47: =if(G47=0,"",E47/G47) -> 1.1 | W47: =if(K47=0,"",E47/K47) -> 0.36666667 | X47: =if(F47=0,"",(E47/F47)*100) -> 6.4102564 | Y47: {=_xlfn.XLOOKUP(A47,'Video Database'!L:L,'Video Database'!M:M,"")} -> Bottom of Funnel
A48: =A47+1 -> 47 | B48: {=_xlfn.XLOOKUP(A48,'Video Database'!L:L,'Video Database'!D:D,"")} -> Erin | C48: {=_xlfn.XLOOKUP(A48,'Video Database'!L:L,'Video Database'!E:E,"")} -> Account 4 | D48: {=_xlfn.XLOOKUP(A48,'Video Database'!L:L,'Video Database'!G:G,"")} -> Stainless Steel Gua Sha | E48: {=_xlfn.XLOOKUP(A48,'Video Database'!L:L,'Video Database'!H:H,"")} -> 1.1 | F48: 0 | G48: 0 | H48: {=_xlfn.XLOOKUP(A48,'Video Database'!L:L,'Video Database'!A:A,"")} -> 46182 | I48: 46201 | J48: 0 | L48: =M48 | O48: =iferror(K48/L48, NA()) -> #N/A | P48: =iferror(G48/K48, NA()) -> #N/A | Q48: =iferror(J48/G48,NA()) -> #N/A | R48: =iferror(F48/G48,NA()) -> #N/A | S48: =J48-E48 -> -1.1 | T48: =if(E48=0,"",S48/E48) -> -1 | U48: =iferror(S48/J48,na()) -> #N/A | V48: =if(G48=0,"",E48/G48) | W48: =if(K48=0,"",E48/K48) | X48: =if(F48=0,"",(E48/F48)*100) | Y48: {=_xlfn.XLOOKUP(A48,'Video Database'!L:L,'Video Database'!M:M,"")} -> Bottom of Funnel
A49: =A48+1 -> 48 | B49: {=_xlfn.XLOOKUP(A49,'Video Database'!L:L,'Video Database'!D:D,"")} -> Erin | C49: {=_xlfn.XLOOKUP(A49,'Video Database'!L:L,'Video Database'!E:E,"")} -> Account 4 | D49: {=_xlfn.XLOOKUP(A49,'Video Database'!L:L,'Video Database'!G:G,"")} -> Stainless Steel Gua Sha | E49: {=_xlfn.XLOOKUP(A49,'Video Database'!L:L,'Video Database'!H:H,"")} -> 1.1 | F49: 0 | G49: 0 | H49: {=_xlfn.XLOOKUP(A49,'Video Database'!L:L,'Video Database'!A:A,"")} -> 46182 | I49: 46201 | J49: 0 | L49: =M49 | O49: =iferror(K49/L49, NA()) -> #N/A | P49: =iferror(G49/K49, NA()) -> #N/A | Q49: =iferror(J49/G49,NA()) -> #N/A | R49: =iferror(F49/G49,NA()) -> #N/A | S49: =J49-E49 -> -1.1 | T49: =if(E49=0,"",S49/E49) -> -1 | U49: =iferror(S49/J49,na()) -> #N/A | V49: =if(G49=0,"",E49/G49) | W49: =if(K49=0,"",E49/K49) | X49: =if(F49=0,"",(E49/F49)*100) | Y49: {=_xlfn.XLOOKUP(A49,'Video Database'!L:L,'Video Database'!M:M,"")} -> Bottom of Funnel
A50: =A49+1 -> 49 | B50: {=_xlfn.XLOOKUP(A50,'Video Database'!L:L,'Video Database'!D:D,"")} -> Erin | C50: {=_xlfn.XLOOKUP(A50,'Video Database'!L:L,'Video Database'!E:E,"")} -> Account 4 | D50: {=_xlfn.XLOOKUP(A50,'Video Database'!L:L,'Video Database'!G:G,"")} -> Stainless Steel Gua Sha | E50: {=_xlfn.XLOOKUP(A50,'Video Database'!L:L,'Video Database'!H:H,"")} -> 1.1 | F50: 0 | G50: 0 | H50: {=_xlfn.XLOOKUP(A50,'Video Database'!L:L,'Video Database'!A:A,"")} -> 46182 | I50: 46201 | J50: 0 | L50: =M50 | O50: =iferror(K50/L50, NA()) -> #N/A | P50: =iferror(G50/K50, NA()) -> #N/A | Q50: =iferror(J50/G50,NA()) -> #N/A | R50: =iferror(F50/G50,NA()) -> #N/A | S50: =J50-E50 -> -1.1 | T50: =if(E50=0,"",S50/E50) -> -1 | U50: =iferror(S50/J50,na()) -> #N/A | V50: =if(G50=0,"",E50/G50) | W50: =if(K50=0,"",E50/K50) | X50: =if(F50=0,"",(E50/F50)*100) | Y50: {=_xlfn.XLOOKUP(A50,'Video Database'!L:L,'Video Database'!M:M,"")} -> Bottom of Funnel
A51: =A50+1 -> 50 | B51: {=_xlfn.XLOOKUP(A51,'Video Database'!L:L,'Video Database'!D:D,"")} -> Erin | C51: {=_xlfn.XLOOKUP(A51,'Video Database'!L:L,'Video Database'!E:E,"")} -> Account 4 | D51: {=_xlfn.XLOOKUP(A51,'Video Database'!L:L,'Video Database'!G:G,"")} -> Stainless Steel Gua Sha | E51: {=_xlfn.XLOOKUP(A51,'Video Database'!L:L,'Video Database'!H:H,"")} -> 1.1 | F51: 0 | G51: 0 | H51: {=_xlfn.XLOOKUP(A51,'Video Database'!L:L,'Video Database'!A:A,"")} -> 46182 | I51: 46201 | J51: 0 | L51: =M51 | O51: =iferror(K51/L51, NA()) -> #N/A | P51: =iferror(G51/K51, NA()) -> #N/A | Q51: =iferror(J51/G51,NA()) -> #N/A | R51: =iferror(F51/G51,NA()) -> #N/A | S51: =J51-E51 -> -1.1 | T51: =if(E51=0,"",S51/E51) -> -1 | U51: =iferror(S51/J51,na()) -> #N/A | V51: =if(G51=0,"",E51/G51) | W51: =if(K51=0,"",E51/K51) | X51: =if(F51=0,"",(E51/F51)*100) | Y51: {=_xlfn.XLOOKUP(A51,'Video Database'!L:L,'Video Database'!M:M,"")} -> Bottom of Funnel
A52: =A51+1 -> 51 | B52: {=_xlfn.XLOOKUP(A52,'Video Database'!L:L,'Video Database'!D:D,"")} -> Erin | C52: {=_xlfn.XLOOKUP(A52,'Video Database'!L:L,'Video Database'!E:E,"")} -> Account 4 | D52: {=_xlfn.XLOOKUP(A52,'Video Database'!L:L,'Video Database'!G:G,"")} -> Stainless Steel Gua Sha | E52: {=_xlfn.XLOOKUP(A52,'Video Database'!L:L,'Video Database'!H:H,"")} -> 1.1 | F52: 0 | G52: 0 | H52: {=_xlfn.XLOOKUP(A52,'Video Database'!L:L,'Video Database'!A:A,"")} -> 46182 | I52: 46201 | J52: 0 | L52: =M52 | O52: =iferror(K52/L52, NA()) -> #N/A | P52: =iferror(G52/K52, NA()) -> #N/A | Q52: =iferror(J52/G52,NA()) -> #N/A | R52: =iferror(F52/G52,NA()) -> #N/A | S52: =J52-E52 -> -1.1 | T52: =if(E52=0,"",S52/E52) -> -1 | U52: =iferror(S52/J52,na()) -> #N/A | V52: =if(G52=0,"",E52/G52) | W52: =if(K52=0,"",E52/K52) | X52: =if(F52=0,"",(E52/F52)*100) | Y52: {=_xlfn.XLOOKUP(A52,'Video Database'!L:L,'Video Database'!M:M,"")} -> Bottom of Funnel
A53: =A52+1 -> 52 | B53: {=_xlfn.XLOOKUP(A53,'Video Database'!L:L,'Video Database'!D:D,"")} -> Erin | C53: {=_xlfn.XLOOKUP(A53,'Video Database'!L:L,'Video Database'!E:E,"")} -> Account 4 | D53: {=_xlfn.XLOOKUP(A53,'Video Database'!L:L,'Video Database'!G:G,"")} -> Stainless Steel Gua Sha | E53: {=_xlfn.XLOOKUP(A53,'Video Database'!L:L,'Video Database'!H:H,"")} -> 1.1 | F53: 0 | G53: 0 | H53: {=_xlfn.XLOOKUP(A53,'Video Database'!L:L,'Video Database'!A:A,"")} -> 46182 | I53: 46201 | J53: 0 | L53: =M53 | O53: =iferror(K53/L53, NA()) -> #N/A | P53: =iferror(G53/K53, NA()) -> #N/A | Q53: =iferror(J53/G53,NA()) -> #N/A | R53: =iferror(F53/G53,NA()) -> #N/A | S53: =J53-E53 -> -1.1 | T53: =if(E53=0,"",S53/E53) -> -1 | U53: =iferror(S53/J53,na()) -> #N/A | V53: =if(G53=0,"",E53/G53) | W53: =if(K53=0,"",E53/K53) | X53: =if(F53=0,"",(E53/F53)*100) | Y53: {=_xlfn.XLOOKUP(A53,'Video Database'!L:L,'Video Database'!M:M,"")} -> Bottom of Funnel
A54: =A53+1 -> 53 | B54: {=_xlfn.XLOOKUP(A54,'Video Database'!L:L,'Video Database'!D:D,"")} -> Erin | C54: {=_xlfn.XLOOKUP(A54,'Video Database'!L:L,'Video Database'!E:E,"")} -> Account 4 | D54: {=_xlfn.XLOOKUP(A54,'Video Database'!L:L,'Video Database'!G:G,"")} -> Stainless Steel Gua Sha | E54: {=_xlfn.XLOOKUP(A54,'Video Database'!L:L,'Video Database'!H:H,"")} -> 1.1 | F54: 0 | G54: 0 | H54: {=_xlfn.XLOOKUP(A54,'Video Database'!L:L,'Video Database'!A:A,"")} -> 46182 | I54: 46201 | J54: 0 | L54: =M54 | O54: =iferror(K54/L54, NA()) -> #N/A | P54: =iferror(G54/K54, NA()) -> #N/A | Q54: =iferror(J54/G54,NA()) -> #N/A | R54: =iferror(F54/G54,NA()) -> #N/A | S54: =J54-E54 -> -1.1 | T54: =if(E54=0,"",S54/E54) -> -1 | U54: =iferror(S54/J54,na()) -> #N/A | V54: =if(G54=0,"",E54/G54) | W54: =if(K54=0,"",E54/K54) | X54: =if(F54=0,"",(E54/F54)*100) | Y54: {=_xlfn.XLOOKUP(A54,'Video Database'!L:L,'Video Database'!M:M,"")} -> Bottom of Funnel
A55: =A54+1 -> 54 | B55: {=_xlfn.XLOOKUP(A55,'Video Database'!L:L,'Video Database'!D:D,"")} -> Erin | C55: {=_xlfn.XLOOKUP(A55,'Video Database'!L:L,'Video Database'!E:E,"")} -> Account 4 | D55: {=_xlfn.XLOOKUP(A55,'Video Database'!L:L,'Video Database'!G:G,"")} -> Stainless Steel Gua Sha | E55: {=_xlfn.XLOOKUP(A55,'Video Database'!L:L,'Video Database'!H:H,"")} -> 1.1 | F55: 0 | G55: 0 | H55: {=_xlfn.XLOOKUP(A55,'Video Database'!L:L,'Video Database'!A:A,"")} -> 46182 | I55: 46201 | J55: 0 | L55: =M55 | O55: =iferror(K55/L55, NA()) -> #N/A | P55: =iferror(G55/K55, NA()) -> #N/A | Q55: =iferror(J55/G55,NA()) -> #N/A | R55: =iferror(F55/G55,NA()) -> #N/A | S55: =J55-E55 -> -1.1 | T55: =if(E55=0,"",S55/E55) -> -1 | U55: =iferror(S55/J55,na()) -> #N/A | V55: =if(G55=0,"",E55/G55) | W55: =if(K55=0,"",E55/K55) | X55: =if(F55=0,"",(E55/F55)*100) | Y55: {=_xlfn.XLOOKUP(A55,'Video Database'!L:L,'Video Database'!M:M,"")} -> Bottom of Funnel
A56: =A55+1 -> 55 | B56: {=_xlfn.XLOOKUP(A56,'Video Database'!L:L,'Video Database'!D:D,"")} -> Erin | C56: {=_xlfn.XLOOKUP(A56,'Video Database'!L:L,'Video Database'!E:E,"")} -> Account 4 | D56: {=_xlfn.XLOOKUP(A56,'Video Database'!L:L,'Video Database'!G:G,"")} -> Stainless Steel Gua Sha | E56: {=_xlfn.XLOOKUP(A56,'Video Database'!L:L,'Video Database'!H:H,"")} -> 1.1 | F56: 0 | G56: 0 | H56: {=_xlfn.XLOOKUP(A56,'Video Database'!L:L,'Video Database'!A:A,"")} -> 46182 | I56: 46201 | J56: 0 | L56: =M56 | O56: =iferror(K56/L56, NA()) -> #N/A | P56: =iferror(G56/K56, NA()) -> #N/A | Q56: =iferror(J56/G56,NA()) -> #N/A | R56: =iferror(F56/G56,NA()) -> #N/A | S56: =J56-E56 -> -1.1 | T56: =if(E56=0,"",S56/E56) -> -1 | U56: =iferror(S56/J56,na()) -> #N/A | V56: =if(G56=0,"",E56/G56) | W56: =if(K56=0,"",E56/K56) | X56: =if(F56=0,"",(E56/F56)*100) | Y56: {=_xlfn.XLOOKUP(A56,'Video Database'!L:L,'Video Database'!M:M,"")} -> Bottom of Funnel
A57: =A56+1 -> 56 | B57: {=_xlfn.XLOOKUP(A57,'Video Database'!L:L,'Video Database'!D:D,"")} -> Erin | C57: {=_xlfn.XLOOKUP(A57,'Video Database'!L:L,'Video Database'!E:E,"")} -> Account 4 | D57: {=_xlfn.XLOOKUP(A57,'Video Database'!L:L,'Video Database'!G:G,"")} -> Stainless Steel Gua Sha | E57: {=_xlfn.XLOOKUP(A57,'Video Database'!L:L,'Video Database'!H:H,"")} -> 1.1 | F57: 0 | G57: 0 | H57: {=_xlfn.XLOOKUP(A57,'Video Database'!L:L,'Video Database'!A:A,"")} -> 46182 | I57: 46201 | J57: 0 | L57: =M57 | O57: =iferror(K57/L57, NA()) -> #N/A | P57: =iferror(G57/K57, NA()) -> #N/A | Q57: =iferror(J57/G57,NA()) -> #N/A | R57: =iferror(F57/G57,NA()) -> #N/A | S57: =J57-E57 -> -1.1 | T57: =if(E57=0,"",S57/E57) -> -1 | U57: =iferror(S57/J57,na()) -> #N/A | V57: =if(G57=0,"",E57/G57) | W57: =if(K57=0,"",E57/K57) | X57: =if(F57=0,"",(E57/F57)*100) | Y57: {=_xlfn.XLOOKUP(A57,'Video Database'!L:L,'Video Database'!M:M,"")} -> Bottom of Funnel
A58: =A57+1 -> 57 | B58: {=_xlfn.XLOOKUP(A58,'Video Database'!L:L,'Video Database'!D:D,"")} -> Erin | C58: {=_xlfn.XLOOKUP(A58,'Video Database'!L:L,'Video Database'!E:E,"")} -> Account 4 | D58: {=_xlfn.XLOOKUP(A58,'Video Database'!L:L,'Video Database'!G:G,"")} -> Stainless Steel Gua Sha | E58: {=_xlfn.XLOOKUP(A58,'Video Database'!L:L,'Video Database'!H:H,"")} -> 1.1 | F58: 0 | G58: 0 | H58: {=_xlfn.XLOOKUP(A58,'Video Database'!L:L,'Video Database'!A:A,"")} -> 46182 | I58: 46201 | J58: 0 | L58: =M58 | O58: =iferror(K58/L58, NA()) -> #N/A | P58: =iferror(G58/K58, NA()) -> #N/A | Q58: =iferror(J58/G58,NA()) -> #N/A | R58: =iferror(F58/G58,NA()) -> #N/A | S58: =J58-E58 -> -1.1 | T58: =if(E58=0,"",S58/E58) -> -1 | U58: =iferror(S58/J58,na()) -> #N/A | V58: =if(G58=0,"",E58/G58) | W58: =if(K58=0,"",E58/K58) | X58: =if(F58=0,"",(E58/F58)*100) | Y58: {=_xlfn.XLOOKUP(A58,'Video Database'!L:L,'Video Database'!M:M,"")} -> Bottom of Funnel
A59: =A58+1 -> 58 | B59: {=_xlfn.XLOOKUP(A59,'Video Database'!L:L,'Video Database'!D:D,"")} -> Erin | C59: {=_xlfn.XLOOKUP(A59,'Video Database'!L:L,'Video Database'!E:E,"")} -> Account 4 | D59: {=_xlfn.XLOOKUP(A59,'Video Database'!L:L,'Video Database'!G:G,"")} -> Stainless Steel Gua Sha | E59: {=_xlfn.XLOOKUP(A59,'Video Database'!L:L,'Video Database'!H:H,"")} -> 1.1 | F59: 0 | G59: 0 | H59: {=_xlfn.XLOOKUP(A59,'Video Database'!L:L,'Video Database'!A:A,"")} -> 46182 | I59: 46201 | J59: 0 | L59: =M59 | O59: =iferror(K59/L59, NA()) -> #N/A | P59: =iferror(G59/K59, NA()) -> #N/A | Q59: =iferror(J59/G59,NA()) -> #N/A | R59: =iferror(F59/G59,NA()) -> #N/A | S59: =J59-E59 -> -1.1 | T59: =if(E59=0,"",S59/E59) -> -1 | U59: =iferror(S59/J59,na()) -> #N/A | V59: =if(G59=0,"",E59/G59) | W59: =if(K59=0,"",E59/K59) | X59: =if(F59=0,"",(E59/F59)*100) | Y59: {=_xlfn.XLOOKUP(A59,'Video Database'!L:L,'Video Database'!M:M,"")} -> Bottom of Funnel
... A65: =A64+1 -> 64 | B65: {=_xlfn.XLOOKUP(A65,'Video Database'!L:L,'Video Database'!D:D,"")} -> Blakely | C65: {=_xlfn.XLOOKUP(A65,'Video Database'!L:L,'Video Database'!E:E,"")} -> Account 4 | D65: {=_xlfn.XLOOKUP(A65,'Video Database'!L:L,'Video Database'!G:G,"")} -> DR.DENT Purple Mouthwash | E65: {=_xlfn.XLOOKUP(A65,'Video Database'!L:L,'Video Database'!H:H,"")} -> 0.11 | F65: 0 | G65: 0 | H65: {=_xlfn.XLOOKUP(A65,'Video Database'!L:L,'Video Database'!A:A,"")} -> 46183 | I65: 46201 | J65: 0 | L65: =M65 | O65: =iferror(K65/L65, NA()) -> #N/A | P65: =iferror(G65/K65, NA()) -> #N/A | Q65: =iferror(J65/G65,NA()) -> #N/A | R65: =iferror(F65/G65,NA()) -> #N/A | S65: =J65-E65 -> -0.11 | T65: =if(E65=0,"",S65/E65) -> -1 | U65: =iferror(S65/J65,na()) -> #N/A | V65: =if(G65=0,"",E65/G65) | W65: =if(K65=0,"",E65/K65) | X65: =if(F65=0,"",(E65/F65)*100) | Y65: {=_xlfn.XLOOKUP(A65,'Video Database'!L:L,'Video Database'!M:M,"")} -> Bottom of Funnel
A66: =A65+1 -> 65 | B66: {=_xlfn.XLOOKUP(A66,'Video Database'!L:L,'Video Database'!D:D,"")} -> Blakely | C66: {=_xlfn.XLOOKUP(A66,'Video Database'!L:L,'Video Database'!E:E,"")} -> Account 4 | D66: {=_xlfn.XLOOKUP(A66,'Video Database'!L:L,'Video Database'!G:G,"")} -> DR.DENT Purple Mouthwash | E66: {=_xlfn.XLOOKUP(A66,'Video Database'!L:L,'Video Database'!H:H,"")} -> 0.11 | F66: 16.06 | G66: 1 | H66: {=_xlfn.XLOOKUP(A66,'Video Database'!L:L,'Video Database'!A:A,"")} -> 46183 | I66: 46201 | J66: 1.7 | K66: 3 | L66: =M66 -> 498 | M66: 498 | O66: =iferror(K66/L66, NA()) -> 0.0060240964 | P66: =iferror(G66/K66, NA()) -> 0.33333333 | Q66: =iferror(J66/G66,NA()) -> 1.7 | R66: =iferror(F66/G66,NA()) -> 16.06 | S66: =J66-E66 -> 1.59 | T66: =if(E66=0,"",S66/E66) -> 14.454545 | U66: =iferror(S66/J66,na()) -> 0.93529412 | V66: =if(G66=0,"",E66/G66) -> 0.11 | W66: =if(K66=0,"",E66/K66) -> 0.036666667 | X66: =if(F66=0,"",(E66/F66)*100) -> 0.68493151 | Y66: {=_xlfn.XLOOKUP(A66,'Video Database'!L:L,'Video Database'!M:M,"")} -> Bottom of Funnel
A67: =A66+1 -> 66 | B67: {=_xlfn.XLOOKUP(A67,'Video Database'!L:L,'Video Database'!D:D,"")} -> Blakely | C67: {=_xlfn.XLOOKUP(A67,'Video Database'!L:L,'Video Database'!E:E,"")} -> Account 4 | D67: {=_xlfn.XLOOKUP(A67,'Video Database'!L:L,'Video Database'!G:G,"")} -> DR.DENT Purple Mouthwash | E67: {=_xlfn.XLOOKUP(A67,'Video Database'!L:L,'Video Database'!H:H,"")} -> 0.11 | F67: 0 | G67: 0 | H67: {=_xlfn.XLOOKUP(A67,'Video Database'!L:L,'Video Database'!A:A,"")} -> 46183 | I67: 46201 | J67: 0 | L67: =M67 | O67: =iferror(K67/L67, NA()) -> #N/A | P67: =iferror(G67/K67, NA()) -> #N/A | Q67: =iferror(J67/G67,NA()) -> #N/A | R67: =iferror(F67/G67,NA()) -> #N/A | S67: =J67-E67 -> -0.11 | T67: =if(E67=0,"",S67/E67) -> -1 | U67: =iferror(S67/J67,na()) -> #N/A | V67: =if(G67=0,"",E67/G67) | W67: =if(K67=0,"",E67/K67) | X67: =if(F67=0,"",(E67/F67)*100) | Y67: {=_xlfn.XLOOKUP(A67,'Video Database'!L:L,'Video Database'!M:M,"")} -> Bottom of Funnel
A68: =A67+1 -> 67 | B68: {=_xlfn.XLOOKUP(A68,'Video Database'!L:L,'Video Database'!D:D,"")} -> Blakely | C68: {=_xlfn.XLOOKUP(A68,'Video Database'!L:L,'Video Database'!E:E,"")} -> Account 4 | D68: {=_xlfn.XLOOKUP(A68,'Video Database'!L:L,'Video Database'!G:G,"")} -> DR.DENT Purple Mouthwash | E68: {=_xlfn.XLOOKUP(A68,'Video Database'!L:L,'Video Database'!H:H,"")} -> 0.11 | F68: 0 | G68: 0 | H68: {=_xlfn.XLOOKUP(A68,'Video Database'!L:L,'Video Database'!A:A,"")} -> 46183 | I68: 46201 | J68: 0 | L68: =M68 | O68: =iferror(K68/L68, NA()) -> #N/A | P68: =iferror(G68/K68, NA()) -> #N/A | Q68: =iferror(J68/G68,NA()) -> #N/A | R68: =iferror(F68/G68,NA()) -> #N/A | S68: =J68-E68 -> -0.11 | T68: =if(E68=0,"",S68/E68) -> -1 | U68: =iferror(S68/J68,na()) -> #N/A | V68: =if(G68=0,"",E68/G68) | W68: =if(K68=0,"",E68/K68) | X68: =if(F68=0,"",(E68/F68)*100) | Y68: {=_xlfn.XLOOKUP(A68,'Video Database'!L:L,'Video Database'!M:M,"")} -> Bottom of Funnel
A69: =A68+1 -> 68 | B69: {=_xlfn.XLOOKUP(A69,'Video Database'!L:L,'Video Database'!D:D,"")} -> Blakely | C69: {=_xlfn.XLOOKUP(A69,'Video Database'!L:L,'Video Database'!E:E,"")} -> Account 4 | D69: {=_xlfn.XLOOKUP(A69,'Video Database'!L:L,'Video Database'!G:G,"")} -> DR.DENT Purple Mouthwash | E69: {=_xlfn.XLOOKUP(A69,'Video Database'!L:L,'Video Database'!H:H,"")} -> 0.11 | F69: 0 | G69: 0 | H69: {=_xlfn.XLOOKUP(A69,'Video Database'!L:L,'Video Database'!A:A,"")} -> 46183 | I69: 46201 | J69: 0 | L69: =M69 | O69: =iferror(K69/L69, NA()) -> #N/A | P69: =iferror(G69/K69, NA()) -> #N/A | Q69: =iferror(J69/G69,NA()) -> #N/A | R69: =iferror(F69/G69,NA()) -> #N/A | S69: =J69-E69 -> -0.11 | T69: =if(E69=0,"",S69/E69) -> -1 | U69: =iferror(S69/J69,na()) -> #N/A | V69: =if(G69=0,"",E69/G69) | W69: =if(K69=0,"",E69/K69) | X69: =if(F69=0,"",(E69/F69)*100) | Y69: {=_xlfn.XLOOKUP(A69,'Video Database'!L:L,'Video Database'!M:M,"")} -> Bottom of Funnel
A70: =A69+1 -> 69 | B70: {=_xlfn.XLOOKUP(A70,'Video Database'!L:L,'Video Database'!D:D,"")} -> Blakely | C70: {=_xlfn.XLOOKUP(A70,'Video Database'!L:L,'Video Database'!E:E,"")} -> Account 4 | D70: {=_xlfn.XLOOKUP(A70,'Video Database'!L:L,'Video Database'!G:G,"")} -> DR.DENT Purple Mouthwash | E70: {=_xlfn.XLOOKUP(A70,'Video Database'!L:L,'Video Database'!H:H,"")} -> 0.11 | F70: 0 | G70: 0 | H70: {=_xlfn.XLOOKUP(A70,'Video Database'!L:L,'Video Database'!A:A,"")} -> 46183 | I70: 46201 | J70: 0 | L70: =M70 | O70: =iferror(K70/L70, NA()) -> #N/A | P70: =iferror(G70/K70, NA()) -> #N/A | Q70: =iferror(J70/G70,NA()) -> #N/A | R70: =iferror(F70/G70,NA()) -> #N/A | S70: =J70-E70 -> -0.11 | T70: =if(E70=0,"",S70/E70) -> -1 | U70: =iferror(S70/J70,na()) -> #N/A | V70: =if(G70=0,"",E70/G70) | W70: =if(K70=0,"",E70/K70) | X70: =if(F70=0,"",(E70/F70)*100) | Y70: {=_xlfn.XLOOKUP(A70,'Video Database'!L:L,'Video Database'!M:M,"")} -> Bottom of Funnel
A71: =A70+1 -> 70 | B71: {=_xlfn.XLOOKUP(A71,'Video Database'!L:L,'Video Database'!D:D,"")} -> Blakely | C71: {=_xlfn.XLOOKUP(A71,'Video Database'!L:L,'Video Database'!E:E,"")} -> Account 4 | D71: {=_xlfn.XLOOKUP(A71,'Video Database'!L:L,'Video Database'!G:G,"")} -> DR.DENT Purple Mouthwash | E71: {=_xlfn.XLOOKUP(A71,'Video Database'!L:L,'Video Database'!H:H,"")} -> 0.11 | F71: 0 | G71: 0 | H71: {=_xlfn.XLOOKUP(A71,'Video Database'!L:L,'Video Database'!A:A,"")} -> 46183 | I71: 46201 | J71: 0 | L71: =M71 | O71: =iferror(K71/L71, NA()) -> #N/A | P71: =iferror(G71/K71, NA()) -> #N/A | Q71: =iferror(J71/G71,NA()) -> #N/A | R71: =iferror(F71/G71,NA()) -> #N/A | S71: =J71-E71 -> -0.11 | T71: =if(E71=0,"",S71/E71) -> -1 | U71: =iferror(S71/J71,na()) -> #N/A | V71: =if(G71=0,"",E71/G71) | W71: =if(K71=0,"",E71/K71) | X71: =if(F71=0,"",(E71/F71)*100) | Y71: {=_xlfn.XLOOKUP(A71,'Video Database'!L:L,'Video Database'!M:M,"")} -> Bottom of Funnel
A72: =A71+1 -> 71 | B72: {=_xlfn.XLOOKUP(A72,'Video Database'!L:L,'Video Database'!D:D,"")} -> Blakely | C72: {=_xlfn.XLOOKUP(A72,'Video Database'!L:L,'Video Database'!E:E,"")} -> Account 4 | D72: {=_xlfn.XLOOKUP(A72,'Video Database'!L:L,'Video Database'!G:G,"")} -> DR.DENT Purple Mouthwash | E72: {=_xlfn.XLOOKUP(A72,'Video Database'!L:L,'Video Database'!H:H,"")} -> 0.11 | F72: 0 | G72: 0 | H72: {=_xlfn.XLOOKUP(A72,'Video Database'!L:L,'Video Database'!A:A,"")} -> 46183 | I72: 46201 | J72: 0 | L72: =M72 | O72: =iferror(K72/L72, NA()) -> #N/A | P72: =iferror(G72/K72, NA()) -> #N/A | Q72: =iferror(J72/G72,NA()) -> #N/A | R72: =iferror(F72/G72,NA()) -> #N/A | S72: =J72-E72 -> -0.11 | T72: =if(E72=0,"",S72/E72) -> -1 | U72: =iferror(S72/J72,na()) -> #N/A | V72: =if(G72=0,"",E72/G72) | W72: =if(K72=0,"",E72/K72) | X72: =if(F72=0,"",(E72/F72)*100) | Y72: {=_xlfn.XLOOKUP(A72,'Video Database'!L:L,'Video Database'!M:M,"")} -> Bottom of Funnel
A73: =A72+1 -> 72 | B73: {=_xlfn.XLOOKUP(A73,'Video Database'!L:L,'Video Database'!D:D,"")} -> Blakely | C73: {=_xlfn.XLOOKUP(A73,'Video Database'!L:L,'Video Database'!E:E,"")} -> Account 4 | D73: {=_xlfn.XLOOKUP(A73,'Video Database'!L:L,'Video Database'!G:G,"")} -> DR.DENT Purple Mouthwash | E73: {=_xlfn.XLOOKUP(A73,'Video Database'!L:L,'Video Database'!H:H,"")} -> 0.11 | F73: 0 | G73: 0 | H73: {=_xlfn.XLOOKUP(A73,'Video Database'!L:L,'Video Database'!A:A,"")} -> 46183 | I73: 46201 | J73: 0 | L73: =M73 | O73: =iferror(K73/L73, NA()) -> #N/A | P73: =iferror(G73/K73, NA()) -> #N/A | Q73: =iferror(J73/G73,NA()) -> #N/A | R73: =iferror(F73/G73,NA()) -> #N/A | S73: =J73-E73 -> -0.11 | T73: =if(E73=0,"",S73/E73) -> -1 | U73: =iferror(S73/J73,na()) -> #N/A | V73: =if(G73=0,"",E73/G73) | W73: =if(K73=0,"",E73/K73) | X73: =if(F73=0,"",(E73/F73)*100) | Y73: {=_xlfn.XLOOKUP(A73,'Video Database'!L:L,'Video Database'!M:M,"")} -> Bottom of Funnel
A74: =A73+1 -> 73 | B74: {=_xlfn.XLOOKUP(A74,'Video Database'!L:L,'Video Database'!D:D,"")} -> Blakely | C74: {=_xlfn.XLOOKUP(A74,'Video Database'!L:L,'Video Database'!E:E,"")} -> Account 4 | D74: {=_xlfn.XLOOKUP(A74,'Video Database'!L:L,'Video Database'!G:G,"")} -> DR.DENT Purple Mouthwash | E74: {=_xlfn.XLOOKUP(A74,'Video Database'!L:L,'Video Database'!H:H,"")} -> 0.11 | F74: 0 | G74: 0 | H74: {=_xlfn.XLOOKUP(A74,'Video Database'!L:L,'Video Database'!A:A,"")} -> 46183 | I74: 46201 | J74: 0 | L74: =M74 | O74: =iferror(K74/L74, NA()) -> #N/A | P74: =iferror(G74/K74, NA()) -> #N/A | Q74: =iferror(J74/G74,NA()) -> #N/A | R74: =iferror(F74/G74,NA()) -> #N/A | S74: =J74-E74 -> -0.11 | T74: =if(E74=0,"",S74/E74) -> -1 | U74: =iferror(S74/J74,na()) -> #N/A | V74: =if(G74=0,"",E74/G74) | W74: =if(K74=0,"",E74/K74) | X74: =if(F74=0,"",(E74/F74)*100) | Y74: {=_xlfn.XLOOKUP(A74,'Video Database'!L:L,'Video Database'!M:M,"")} -> Bottom of Funnel
A75: =A74+1 -> 74 | B75: {=_xlfn.XLOOKUP(A75,'Video Database'!L:L,'Video Database'!D:D,"")} -> Blakely | C75: {=_xlfn.XLOOKUP(A75,'Video Database'!L:L,'Video Database'!E:E,"")} -> Account 4 | D75: {=_xlfn.XLOOKUP(A75,'Video Database'!L:L,'Video Database'!G:G,"")} -> DR.DENT Purple Mouthwash | E75: {=_xlfn.XLOOKUP(A75,'Video Database'!L:L,'Video Database'!H:H,"")} -> 0.11 | F75: 0 | G75: 0 | H75: {=_xlfn.XLOOKUP(A75,'Video Database'!L:L,'Video Database'!A:A,"")} -> 46183 | I75: 46201 | J75: 0 | L75: =M75 | O75: =iferror(K75/L75, NA()) -> #N/A | P75: =iferror(G75/K75, NA()) -> #N/A | Q75: =iferror(J75/G75,NA()) -> #N/A | R75: =iferror(F75/G75,NA()) -> #N/A | S75: =J75-E75 -> -0.11 | T75: =if(E75=0,"",S75/E75) -> -1 | U75: =iferror(S75/J75,na()) -> #N/A | V75: =if(G75=0,"",E75/G75) | W75: =if(K75=0,"",E75/K75) | X75: =if(F75=0,"",(E75/F75)*100) | Y75: {=_xlfn.XLOOKUP(A75,'Video Database'!L:L,'Video Database'!M:M,"")} -> Bottom of Funnel
A76: =A75+1 -> 75 | B76: {=_xlfn.XLOOKUP(A76,'Video Database'!L:L,'Video Database'!D:D,"")} -> Blakely | C76: {=_xlfn.XLOOKUP(A76,'Video Database'!L:L,'Video Database'!E:E,"")} -> Account 4 | D76: {=_xlfn.XLOOKUP(A76,'Video Database'!L:L,'Video Database'!G:G,"")} -> DR.DENT Purple Mouthwash | E76: {=_xlfn.XLOOKUP(A76,'Video Database'!L:L,'Video Database'!H:H,"")} -> 0.11 | F76: 0 | G76: 0 | H76: {=_xlfn.XLOOKUP(A76,'Video Database'!L:L,'Video Database'!A:A,"")} -> 46183 | I76: 46201 | J76: 0 | L76: =M76 | O76: =iferror(K76/L76, NA()) -> #N/A | P76: =iferror(G76/K76, NA()) -> #N/A | Q76: =iferror(J76/G76,NA()) -> #N/A | R76: =iferror(F76/G76,NA()) -> #N/A | S76: =J76-E76 -> -0.11 | T76: =if(E76=0,"",S76/E76) -> -1 | U76: =iferror(S76/J76,na()) -> #N/A | V76: =if(G76=0,"",E76/G76) | W76: =if(K76=0,"",E76/K76) | X76: =if(F76=0,"",(E76/F76)*100) | Y76: {=_xlfn.XLOOKUP(A76,'Video Database'!L:L,'Video Database'!M:M,"")} -> Bottom of Funnel
A77: =A76+1 -> 76 | B77: {=_xlfn.XLOOKUP(A77,'Video Database'!L:L,'Video Database'!D:D,"")} -> Blakely | C77: {=_xlfn.XLOOKUP(A77,'Video Database'!L:L,'Video Database'!E:E,"")} -> Account 4 | D77: {=_xlfn.XLOOKUP(A77,'Video Database'!L:L,'Video Database'!G:G,"")} -> DR.DENT Purple Mouthwash | E77: {=_xlfn.XLOOKUP(A77,'Video Database'!L:L,'Video Database'!H:H,"")} -> 0.11 | F77: 0 | G77: 0 | H77: {=_xlfn.XLOOKUP(A77,'Video Database'!L:L,'Video Database'!A:A,"")} -> 46183 | I77: 46201 | J77: 0 | L77: =M77 | O77: =iferror(K77/L77, NA()) -> #N/A | P77: =iferror(G77/K77, NA()) -> #N/A | Q77: =iferror(J77/G77,NA()) -> #N/A | R77: =iferror(F77/G77,NA()) -> #N/A | S77: =J77-E77 -> -0.11 | T77: =if(E77=0,"",S77/E77) -> -1 | U77: =iferror(S77/J77,na()) -> #N/A | V77: =if(G77=0,"",E77/G77) | W77: =if(K77=0,"",E77/K77) | X77: =if(F77=0,"",(E77/F77)*100) | Y77: {=_xlfn.XLOOKUP(A77,'Video Database'!L:L,'Video Database'!M:M,"")} -> Bottom of Funnel
A78: =A77+1 -> 77 | B78: {=_xlfn.XLOOKUP(A78,'Video Database'!L:L,'Video Database'!D:D,"")} -> Blakely | C78: {=_xlfn.XLOOKUP(A78,'Video Database'!L:L,'Video Database'!E:E,"")} -> Account 1 | D78: {=_xlfn.XLOOKUP(A78,'Video Database'!L:L,'Video Database'!G:G,"")} -> Goli Women's Complete Multi Gummy | E78: {=_xlfn.XLOOKUP(A78,'Video Database'!L:L,'Video Database'!H:H,"")} -> 0.11 | F78: 0 | G78: 0 | H78: {=_xlfn.XLOOKUP(A78,'Video Database'!L:L,'Video Database'!A:A,"")} -> 46183 | I78: 46201 | J78: 0 | L78: =M78 | O78: =iferror(K78/L78, NA()) -> #N/A | P78: =iferror(G78/K78, NA()) -> #N/A | Q78: =iferror(J78/G78,NA()) -> #N/A | R78: =iferror(F78/G78,NA()) -> #N/A | S78: =J78-E78 -> -0.11 | T78: =if(E78=0,"",S78/E78) -> -1 | U78: =iferror(S78/J78,na()) -> #N/A | V78: =if(G78=0,"",E78/G78) | W78: =if(K78=0,"",E78/K78) | X78: =if(F78=0,"",(E78/F78)*100) | Y78: {=_xlfn.XLOOKUP(A78,'Video Database'!L:L,'Video Database'!M:M,"")} -> Bottom of Funnel
... A95: =A94+1 -> 94 | B95: {=_xlfn.XLOOKUP(A95,'Video Database'!L:L,'Video Database'!D:D,"")} -> Erin | C95: {=_xlfn.XLOOKUP(A95,'Video Database'!L:L,'Video Database'!E:E,"")} -> Account 4 | D95: {=_xlfn.XLOOKUP(A95,'Video Database'!L:L,'Video Database'!G:G,"")} -> LullaBites Natural Sleep Gummies | E95: {=_xlfn.XLOOKUP(A95,'Video Database'!L:L,'Video Database'!H:H,"")} -> 1.1 | F95: 0 | G95: 0 | H95: {=_xlfn.XLOOKUP(A95,'Video Database'!L:L,'Video Database'!A:A,"")} -> 46184 | I95: 46201 | J95: 0 | L95: =M95 | O95: =iferror(K95/L95, NA()) -> #N/A | P95: =iferror(G95/K95, NA()) -> #N/A | Q95: =iferror(J95/G95,NA()) -> #N/A | R95: =iferror(F95/G95,NA()) -> #N/A | S95: =J95-E95 -> -1.1 | T95: =if(E95=0,"",S95/E95) -> -1 | U95: =iferror(S95/J95,na()) -> #N/A | V95: =if(G95=0,"",E95/G95) | W95: =if(K95=0,"",E95/K95) | X95: =if(F95=0,"",(E95/F95)*100) | Y95: {=_xlfn.XLOOKUP(A95,'Video Database'!L:L,'Video Database'!M:M,"")} -> Bottom of Funnel
A96: =A95+1 -> 95 | B96: {=_xlfn.XLOOKUP(A96,'Video Database'!L:L,'Video Database'!D:D,"")} -> Erin | C96: {=_xlfn.XLOOKUP(A96,'Video Database'!L:L,'Video Database'!E:E,"")} -> Account 4 | D96: {=_xlfn.XLOOKUP(A96,'Video Database'!L:L,'Video Database'!G:G,"")} -> LullaBites Natural Sleep Gummies | E96: {=_xlfn.XLOOKUP(A96,'Video Database'!L:L,'Video Database'!H:H,"")} -> 1.1 | F96: 19.99 | G96: 1 | H96: {=_xlfn.XLOOKUP(A96,'Video Database'!L:L,'Video Database'!A:A,"")} -> 46184 | I96: 46201 | J96: 2.5 | K96: 3 | L96: =M96 -> 1000 | M96: 1000 | O96: =iferror(K96/L96, NA()) -> 0.003 | P96: =iferror(G96/K96, NA()) -> 0.33333333 | Q96: =iferror(J96/G96,NA()) -> 2.5 | R96: =iferror(F96/G96,NA()) -> 19.99 | S96: =J96-E96 -> 1.4 | T96: =if(E96=0,"",S96/E96) -> 1.2727273 | U96: =iferror(S96/J96,na()) -> 0.56 | V96: =if(G96=0,"",E96/G96) -> 1.1 | W96: =if(K96=0,"",E96/K96) -> 0.36666667 | X96: =if(F96=0,"",(E96/F96)*100) -> 5.5027514 | Y96: {=_xlfn.XLOOKUP(A96,'Video Database'!L:L,'Video Database'!M:M,"")} -> Bottom of Funnel
A97: =A96+1 -> 96 | B97: {=_xlfn.XLOOKUP(A97,'Video Database'!L:L,'Video Database'!D:D,"")} -> Erin | C97: {=_xlfn.XLOOKUP(A97,'Video Database'!L:L,'Video Database'!E:E,"")} -> Account 4 | D97: {=_xlfn.XLOOKUP(A97,'Video Database'!L:L,'Video Database'!G:G,"")} -> LullaBites Natural Sleep Gummies | E97: {=_xlfn.XLOOKUP(A97,'Video Database'!L:L,'Video Database'!H:H,"")} -> 1.1 | F97: 18.04 | G97: 1 | H97: {=_xlfn.XLOOKUP(A97,'Video Database'!L:L,'Video Database'!A:A,"")} -> 46184 | I97: 46201 | J97: 5 | K97: 2 | L97: =M97 -> 701 | M97: 701 | O97: =iferror(K97/L97, NA()) -> 0.002853067 | P97: =iferror(G97/K97, NA()) -> 0.5 | Q97: =iferror(J97/G97,NA()) -> 5 | R97: =iferror(F97/G97,NA()) -> 18.04 | S97: =J97-E97 -> 3.9 | T97: =if(E97=0,"",S97/E97) -> 3.5454545 | U97: =iferror(S97/J97,na()) -> 0.78 | V97: =if(G97=0,"",E97/G97) -> 1.1 | W97: =if(K97=0,"",E97/K97) -> 0.55 | X97: =if(F97=0,"",(E97/F97)*100) -> 6.097561 | Y97: {=_xlfn.XLOOKUP(A97,'Video Database'!L:L,'Video Database'!M:M,"")} -> Bottom of Funnel
A98: =A97+1 -> 97 | B98: {=_xlfn.XLOOKUP(A98,'Video Database'!L:L,'Video Database'!D:D,"")} -> Erin | C98: {=_xlfn.XLOOKUP(A98,'Video Database'!L:L,'Video Database'!E:E,"")} -> Account 4 | D98: {=_xlfn.XLOOKUP(A98,'Video Database'!L:L,'Video Database'!G:G,"")} -> LullaBites Natural Sleep Gummies | E98: {=_xlfn.XLOOKUP(A98,'Video Database'!L:L,'Video Database'!H:H,"")} -> 1.1 | F98: 0 | G98: 0 | H98: {=_xlfn.XLOOKUP(A98,'Video Database'!L:L,'Video Database'!A:A,"")} -> 46184 | I98: 46201 | J98: 0 | L98: =M98 | O98: =iferror(K98/L98, NA()) -> #N/A | P98: =iferror(G98/K98, NA()) -> #N/A | Q98: =iferror(J98/G98,NA()) -> #N/A | R98: =iferror(F98/G98,NA()) -> #N/A | S98: =J98-E98 -> -1.1 | T98: =if(E98=0,"",S98/E98) -> -1 | U98: =iferror(S98/J98,na()) -> #N/A | V98: =if(G98=0,"",E98/G98) | W98: =if(K98=0,"",E98/K98) | X98: =if(F98=0,"",(E98/F98)*100) | Y98: {=_xlfn.XLOOKUP(A98,'Video Database'!L:L,'Video Database'!M:M,"")} -> Bottom of Funnel
A99: =A98+1 -> 98 | B99: {=_xlfn.XLOOKUP(A99,'Video Database'!L:L,'Video Database'!D:D,"")} -> Erin | C99: {=_xlfn.XLOOKUP(A99,'Video Database'!L:L,'Video Database'!E:E,"")} -> Account 4 | D99: {=_xlfn.XLOOKUP(A99,'Video Database'!L:L,'Video Database'!G:G,"")} -> LullaBites Natural Sleep Gummies | E99: {=_xlfn.XLOOKUP(A99,'Video Database'!L:L,'Video Database'!H:H,"")} -> 1.1 | F99: 0 | G99: 0 | H99: {=_xlfn.XLOOKUP(A99,'Video Database'!L:L,'Video Database'!A:A,"")} -> 46184 | I99: 46201 | J99: 0 | L99: =M99 | O99: =iferror(K99/L99, NA()) -> #N/A | P99: =iferror(G99/K99, NA()) -> #N/A | Q99: =iferror(J99/G99,NA()) -> #N/A | R99: =iferror(F99/G99,NA()) -> #N/A | S99: =J99-E99 -> -1.1 | T99: =if(E99=0,"",S99/E99) -> -1 | U99: =iferror(S99/J99,na()) -> #N/A | V99: =if(G99=0,"",E99/G99) | W99: =if(K99=0,"",E99/K99) | X99: =if(F99=0,"",(E99/F99)*100) | Y99: {=_xlfn.XLOOKUP(A99,'Video Database'!L:L,'Video Database'!M:M,"")} -> Bottom of Funnel
A100: =A99+1 -> 99 | B100: {=_xlfn.XLOOKUP(A100,'Video Database'!L:L,'Video Database'!D:D,"")} -> Erin | C100: {=_xlfn.XLOOKUP(A100,'Video Database'!L:L,'Video Database'!E:E,"")} -> Account 4 | D100: {=_xlfn.XLOOKUP(A100,'Video Database'!L:L,'Video Database'!G:G,"")} -> LullaBites Natural Sleep Gummies | E100: {=_xlfn.XLOOKUP(A100,'Video Database'!L:L,'Video Database'!H:H,"")} -> 1.1 | F100: 0 | G100: 0 | H100: {=_xlfn.XLOOKUP(A100,'Video Database'!L:L,'Video Database'!A:A,"")} -> 46184 | I100: 46201 | J100: 0 | L100: =M100 | O100: =iferror(K100/L100, NA()) -> #N/A | P100: =iferror(G100/K100, NA()) -> #N/A | Q100: =iferror(J100/G100,NA()) -> #N/A | R100: =iferror(F100/G100,NA()) -> #N/A | S100: =J100-E100 -> -1.1 | T100: =if(E100=0,"",S100/E100) -> -1 | U100: =iferror(S100/J100,na()) -> #N/A | V100: =if(G100=0,"",E100/G100) | W100: =if(K100=0,"",E100/K100) | X100: =if(F100=0,"",(E100/F100)*100) | Y100: {=_xlfn.XLOOKUP(A100,'Video Database'!L:L,'Video Database'!M:M,"")} -> Bottom of Funnel
A101: =A100+1 -> 100 | B101: {=_xlfn.XLOOKUP(A101,'Video Database'!L:L,'Video Database'!D:D,"")} -> Erin | C101: {=_xlfn.XLOOKUP(A101,'Video Database'!L:L,'Video Database'!E:E,"")} -> Account 4 | D101: {=_xlfn.XLOOKUP(A101,'Video Database'!L:L,'Video Database'!G:G,"")} -> LullaBites Natural Sleep Gummies | E101: {=_xlfn.XLOOKUP(A101,'Video Database'!L:L,'Video Database'!H:H,"")} -> 1.1 | F101: 0 | G101: 0 | H101: {=_xlfn.XLOOKUP(A101,'Video Database'!L:L,'Video Database'!A:A,"")} -> 46184 | I101: 46201 | J101: 0 | L101: =M101 | O101: =iferror(K101/L101, NA()) -> #N/A | P101: =iferror(G101/K101, NA()) -> #N/A | Q101: =iferror(J101/G101,NA()) -> #N/A | R101: =iferror(F101/G101,NA()) -> #N/A | S101: =J101-E101 -> -1.1 | T101: =if(E101=0,"",S101/E101) -> -1 | U101: =iferror(S101/J101,na()) -> #N/A | V101: =if(G101=0,"",E101/G101) | W101: =if(K101=0,"",E101/K101) | X101: =if(F101=0,"",(E101/F101)*100) | Y101: {=_xlfn.XLOOKUP(A101,'Video Database'!L:L,'Video Database'!M:M,"")} -> Bottom of Funnel
A102: =A101+1 -> 101 | B102: {=_xlfn.XLOOKUP(A102,'Video Database'!L:L,'Video Database'!D:D,"")} -> Erin | C102: {=_xlfn.XLOOKUP(A102,'Video Database'!L:L,'Video Database'!E:E,"")} -> Account 4 | D102: {=_xlfn.XLOOKUP(A102,'Video Database'!L:L,'Video Database'!G:G,"")} -> LullaBites Natural Sleep Gummies | E102: {=_xlfn.XLOOKUP(A102,'Video Database'!L:L,'Video Database'!H:H,"")} -> 1.1 | F102: 0 | G102: 0 | H102: {=_xlfn.XLOOKUP(A102,'Video Database'!L:L,'Video Database'!A:A,"")} -> 46184 | I102: 46201 | J102: 0 | L102: =M102 | O102: =iferror(K102/L102, NA()) -> #N/A | P102: =iferror(G102/K102, NA()) -> #N/A | Q102: =iferror(J102/G102,NA()) -> #N/A | R102: =iferror(F102/G102,NA()) -> #N/A | S102: =J102-E102 -> -1.1 | T102: =if(E102=0,"",S102/E102) -> -1 | U102: =iferror(S102/J102,na()) -> #N/A | V102: =if(G102=0,"",E102/G102) | W102: =if(K102=0,"",E102/K102) | X102: =if(F102=0,"",(E102/F102)*100) | Y102: {=_xlfn.XLOOKUP(A102,'Video Database'!L:L,'Video Database'!M:M,"")} -> Bottom of Funnel
A103: =A102+1 -> 102 | B103: {=_xlfn.XLOOKUP(A103,'Video Database'!L:L,'Video Database'!D:D,"")} -> Erin | C103: {=_xlfn.XLOOKUP(A103,'Video Database'!L:L,'Video Database'!E:E,"")} -> Account 4 | D103: {=_xlfn.XLOOKUP(A103,'Video Database'!L:L,'Video Database'!G:G,"")} -> LullaBites Natural Sleep Gummies | E103: {=_xlfn.XLOOKUP(A103,'Video Database'!L:L,'Video Database'!H:H,"")} -> 1.1 | F103: 0 | G103: 0 | H103: {=_xlfn.XLOOKUP(A103,'Video Database'!L:L,'Video Database'!A:A,"")} -> 46184 | I103: 46201 | J103: 0 | L103: =M103 | O103: =iferror(K103/L103, NA()) -> #N/A | P103: =iferror(G103/K103, NA()) -> #N/A | Q103: =iferror(J103/G103,NA()) -> #N/A | R103: =iferror(F103/G103,NA()) -> #N/A | S103: =J103-E103 -> -1.1 | T103: =if(E103=0,"",S103/E103) -> -1 | U103: =iferror(S103/J103,na()) -> #N/A | V103: =if(G103=0,"",E103/G103) | W103: =if(K103=0,"",E103/K103) | X103: =if(F103=0,"",(E103/F103)*100) | Y103: {=_xlfn.XLOOKUP(A103,'Video Database'!L:L,'Video Database'!M:M,"")} -> Bottom of Funnel
A104: =A103+1 -> 103 | B104: {=_xlfn.XLOOKUP(A104,'Video Database'!L:L,'Video Database'!D:D,"")} -> Erin | C104: {=_xlfn.XLOOKUP(A104,'Video Database'!L:L,'Video Database'!E:E,"")} -> Account 4 | D104: {=_xlfn.XLOOKUP(A104,'Video Database'!L:L,'Video Database'!G:G,"")} -> LullaBites Natural Sleep Gummies | E104: {=_xlfn.XLOOKUP(A104,'Video Database'!L:L,'Video Database'!H:H,"")} -> 1.1 | F104: 0 | G104: 0 | H104: {=_xlfn.XLOOKUP(A104,'Video Database'!L:L,'Video Database'!A:A,"")} -> 46184 | I104: 46201 | J104: 0 | L104: =M104 | O104: =iferror(K104/L104, NA()) -> #N/A | P104: =iferror(G104/K104, NA()) -> #N/A | Q104: =iferror(J104/G104,NA()) -> #N/A | R104: =iferror(F104/G104,NA()) -> #N/A | S104: =J104-E104 -> -1.1 | T104: =if(E104=0,"",S104/E104) -> -1 | U104: =iferror(S104/J104,na()) -> #N/A | V104: =if(G104=0,"",E104/G104) | W104: =if(K104=0,"",E104/K104) | X104: =if(F104=0,"",(E104/F104)*100) | Y104: {=_xlfn.XLOOKUP(A104,'Video Database'!L:L,'Video Database'!M:M,"")} -> Bottom of Funnel
A105: =A104+1 -> 104 | B105: {=_xlfn.XLOOKUP(A105,'Video Database'!L:L,'Video Database'!D:D,"")} -> Erin | C105: {=_xlfn.XLOOKUP(A105,'Video Database'!L:L,'Video Database'!E:E,"")} -> Account 4 | D105: {=_xlfn.XLOOKUP(A105,'Video Database'!L:L,'Video Database'!G:G,"")} -> LullaBites Natural Sleep Gummies | E105: {=_xlfn.XLOOKUP(A105,'Video Database'!L:L,'Video Database'!H:H,"")} -> 1.1 | F105: 0 | G105: 0 | H105: {=_xlfn.XLOOKUP(A105,'Video Database'!L:L,'Video Database'!A:A,"")} -> 46184 | I105: 46201 | J105: 0 | L105: =M105 | O105: =iferror(K105/L105, NA()) -> #N/A | P105: =iferror(G105/K105, NA()) -> #N/A | Q105: =iferror(J105/G105,NA()) -> #N/A | R105: =iferror(F105/G105,NA()) -> #N/A | S105: =J105-E105 -> -1.1 | T105: =if(E105=0,"",S105/E105) -> -1 | U105: =iferror(S105/J105,na()) -> #N/A | V105: =if(G105=0,"",E105/G105) | W105: =if(K105=0,"",E105/K105) | X105: =if(F105=0,"",(E105/F105)*100) | Y105: {=_xlfn.XLOOKUP(A105,'Video Database'!L:L,'Video Database'!M:M,"")} -> Bottom of Funnel
A106: =A105+1 -> 105 | B106: {=_xlfn.XLOOKUP(A106,'Video Database'!L:L,'Video Database'!D:D,"")} -> Erin | C106: {=_xlfn.XLOOKUP(A106,'Video Database'!L:L,'Video Database'!E:E,"")} -> Account 4 | D106: {=_xlfn.XLOOKUP(A106,'Video Database'!L:L,'Video Database'!G:G,"")} -> LullaBites Natural Sleep Gummies | E106: {=_xlfn.XLOOKUP(A106,'Video Database'!L:L,'Video Database'!H:H,"")} -> 1.1 | F106: 0 | G106: 0 | H106: {=_xlfn.XLOOKUP(A106,'Video Database'!L:L,'Video Database'!A:A,"")} -> 46184 | I106: 46201 | J106: 0 | L106: =M106 | O106: =iferror(K106/L106, NA()) -> #N/A | P106: =iferror(G106/K106, NA()) -> #N/A | Q106: =iferror(J106/G106,NA()) -> #N/A | R106: =iferror(F106/G106,NA()) -> #N/A | S106: =J106-E106 -> -1.1 | T106: =if(E106=0,"",S106/E106) -> -1 | U106: =iferror(S106/J106,na()) -> #N/A | V106: =if(G106=0,"",E106/G106) | W106: =if(K106=0,"",E106/K106) | X106: =if(F106=0,"",(E106/F106)*100) | Y106: {=_xlfn.XLOOKUP(A106,'Video Database'!L:L,'Video Database'!M:M,"")} -> Bottom of Funnel
A107: =A106+1 -> 106 | B107: {=_xlfn.XLOOKUP(A107,'Video Database'!L:L,'Video Database'!D:D,"")} -> Erin | C107: {=_xlfn.XLOOKUP(A107,'Video Database'!L:L,'Video Database'!E:E,"")} -> Account 4 | D107: {=_xlfn.XLOOKUP(A107,'Video Database'!L:L,'Video Database'!G:G,"")} -> LullaBites Natural Sleep Gummies | E107: {=_xlfn.XLOOKUP(A107,'Video Database'!L:L,'Video Database'!H:H,"")} -> 1.1 | F107: 0 | G107: 0 | H107: {=_xlfn.XLOOKUP(A107,'Video Database'!L:L,'Video Database'!A:A,"")} -> 46184 | I107: 46201 | J107: 0 | L107: =M107 | O107: =iferror(K107/L107, NA()) -> #N/A | P107: =iferror(G107/K107, NA()) -> #N/A | Q107: =iferror(J107/G107,NA()) -> #N/A | R107: =iferror(F107/G107,NA()) -> #N/A | S107: =J107-E107 -> -1.1 | T107: =if(E107=0,"",S107/E107) -> -1 | U107: =iferror(S107/J107,na()) -> #N/A | V107: =if(G107=0,"",E107/G107) | W107: =if(K107=0,"",E107/K107) | X107: =if(F107=0,"",(E107/F107)*100) | Y107: {=_xlfn.XLOOKUP(A107,'Video Database'!L:L,'Video Database'!M:M,"")} -> Bottom of Funnel
A108: =A107+1 -> 107 | B108: {=_xlfn.XLOOKUP(A108,'Video Database'!L:L,'Video Database'!D:D,"")} -> Blakely | C108: {=_xlfn.XLOOKUP(A108,'Video Database'!L:L,'Video Database'!E:E,"")} -> Account 1 | D108: {=_xlfn.XLOOKUP(A108,'Video Database'!L:L,'Video Database'!G:G,"")} -> Goli Women's Complete Multi Gummy | E108: {=_xlfn.XLOOKUP(A108,'Video Database'!L:L,'Video Database'!H:H,"")} -> 0.11 | F108: 0 | G108: 0 | H108: {=_xlfn.XLOOKUP(A108,'Video Database'!L:L,'Video Database'!A:A,"")} -> 46185 | I108: 46201 | J108: 0 | L108: =M108 | O108: =iferror(K108/L108, NA()) -> #N/A | P108: =iferror(G108/K108, NA()) -> #N/A | Q108: =iferror(J108/G108,NA()) -> #N/A | R108: =iferror(F108/G108,NA()) -> #N/A | S108: =J108-E108 -> -0.11 | T108: =if(E108=0,"",S108/E108) -> -1 | U108: =iferror(S108/J108,na()) -> #N/A | V108: =if(G108=0,"",E108/G108) | W108: =if(K108=0,"",E108/K108) | X108: =if(F108=0,"",(E108/F108)*100) | Y108: {=_xlfn.XLOOKUP(A108,'Video Database'!L:L,'Video Database'!M:M,"")} -> Bottom of Funnel
A109: =A108+1 -> 108 | B109: {=_xlfn.XLOOKUP(A109,'Video Database'!L:L,'Video Database'!D:D,"")} -> Blakely | C109: {=_xlfn.XLOOKUP(A109,'Video Database'!L:L,'Video Database'!E:E,"")} -> Account 1 | D109: {=_xlfn.XLOOKUP(A109,'Video Database'!L:L,'Video Database'!G:G,"")} -> Goli Women's Complete Multi Gummy | E109: {=_xlfn.XLOOKUP(A109,'Video Database'!L:L,'Video Database'!H:H,"")} -> 0.11 | F109: 0 | G109: 0 | H109: {=_xlfn.XLOOKUP(A109,'Video Database'!L:L,'Video Database'!A:A,"")} -> 46185 | I109: 46201 | J109: 0 | L109: =M109 | O109: =iferror(K109/L109, NA()) -> #N/A | P109: =iferror(G109/K109, NA()) -> #N/A | Q109: =iferror(J109/G109,NA()) -> #N/A | R109: =iferror(F109/G109,NA()) -> #N/A | S109: =J109-E109 -> -0.11 | T109: =if(E109=0,"",S109/E109) -> -1 | U109: =iferror(S109/J109,na()) -> #N/A | V109: =if(G109=0,"",E109/G109) | W109: =if(K109=0,"",E109/K109) | X109: =if(F109=0,"",(E109/F109)*100) | Y109: {=_xlfn.XLOOKUP(A109,'Video Database'!L:L,'Video Database'!M:M,"")} -> Bottom of Funnel
... A222: =A221+1 -> 221 | B222: {=_xlfn.XLOOKUP(A222,'Video Database'!L:L,'Video Database'!D:D,"")} -> Brittney | C222: {=_xlfn.XLOOKUP(A222,'Video Database'!L:L,'Video Database'!E:E,"")} -> Account 4 | D222: {=_xlfn.XLOOKUP(A222,'Video Database'!L:L,'Video Database'!G:G,"")} -> Gruns Greens Popsicle Firecracker Gummies | E222: {=_xlfn.XLOOKUP(A222,'Video Database'!L:L,'Video Database'!H:H,"")} -> 1.1 | F222: 0 | G222: 0 | H222: {=_xlfn.XLOOKUP(A222,'Video Database'!L:L,'Video Database'!A:A,"")} -> 46186 | I222: 46201 | J222: 0 | L222: =M222 | O222: =iferror(K222/L222, NA()) -> #N/A | P222: =iferror(G222/K222, NA()) -> #N/A | Q222: =iferror(J222/G222,NA()) -> #N/A | R222: =iferror(F222/G222,NA()) -> #N/A | S222: =J222-E222 -> -1.1 | T222: =if(E222=0,"",S222/E222) -> -1 | U222: =iferror(S222/J222,na()) -> #N/A | V222: =if(G222=0,"",E222/G222) | W222: =if(K222=0,"",E222/K222) | X222: =if(F222=0,"",(E222/F222)*100) | Y222: {=_xlfn.XLOOKUP(A222,'Video Database'!L:L,'Video Database'!M:M,"")} -> Bottom of Funnel
A223: =A222+1 -> 222 | B223: {=_xlfn.XLOOKUP(A223,'Video Database'!L:L,'Video Database'!D:D,"")} -> Brittney | C223: {=_xlfn.XLOOKUP(A223,'Video Database'!L:L,'Video Database'!E:E,"")} -> Account 4 | D223: {=_xlfn.XLOOKUP(A223,'Video Database'!L:L,'Video Database'!G:G,"")} -> Gruns Greens Popsicle Firecracker Gummies | E223: {=_xlfn.XLOOKUP(A223,'Video Database'!L:L,'Video Database'!H:H,"")} -> 1.1 | F223: 17.49 | G223: 1 | H223: {=_xlfn.XLOOKUP(A223,'Video Database'!L:L,'Video Database'!A:A,"")} -> 46186 | I223: 46201 | J223: 2.62 | K223: 2 | L223: =M223 -> 1200 | M223: 1200 | O223: =iferror(K223/L223, NA()) -> 0.0016666667 | P223: =iferror(G223/K223, NA()) -> 0.5 | Q223: =iferror(J223/G223,NA()) -> 2.62 | R223: =iferror(F223/G223,NA()) -> 17.49 | S223: =J223-E223 -> 1.52 | T223: =if(E223=0,"",S223/E223) -> 1.3818182 | U223: =iferror(S223/J223,na()) -> 0.58015267 | V223: =if(G223=0,"",E223/G223) -> 1.1 | W223: =if(K223=0,"",E223/K223) -> 0.55 | X223: =if(F223=0,"",(E223/F223)*100) -> 6.2893082 | Y223: {=_xlfn.XLOOKUP(A223,'Video Database'!L:L,'Video Database'!M:M,"")} -> Bottom of Funnel
A224: =A223+1 -> 223 | B224: {=_xlfn.XLOOKUP(A224,'Video Database'!L:L,'Video Database'!D:D,"")} -> Brittney | C224: {=_xlfn.XLOOKUP(A224,'Video Database'!L:L,'Video Database'!E:E,"")} -> Account 4 | D224: {=_xlfn.XLOOKUP(A224,'Video Database'!L:L,'Video Database'!G:G,"")} -> Gruns Greens Popsicle Firecracker Gummies | E224: {=_xlfn.XLOOKUP(A224,'Video Database'!L:L,'Video Database'!H:H,"")} -> 1.1 | F224: 0 | G224: 0 | H224: {=_xlfn.XLOOKUP(A224,'Video Database'!L:L,'Video Database'!A:A,"")} -> 46186 | I224: 46201 | J224: 0 | L224: =M224 | O224: =iferror(K224/L224, NA()) -> #N/A | P224: =iferror(G224/K224, NA()) -> #N/A | Q224: =iferror(J224/G224,NA()) -> #N/A | R224: =iferror(F224/G224,NA()) -> #N/A | S224: =J224-E224 -> -1.1 | T224: =if(E224=0,"",S224/E224) -> -1 | U224: =iferror(S224/J224,na()) -> #N/A | V224: =if(G224=0,"",E224/G224) | W224: =if(K224=0,"",E224/K224) | X224: =if(F224=0,"",(E224/F224)*100) | Y224: {=_xlfn.XLOOKUP(A224,'Video Database'!L:L,'Video Database'!M:M,"")} -> Bottom of Funnel
A225: =A224+1 -> 224 | B225: {=_xlfn.XLOOKUP(A225,'Video Database'!L:L,'Video Database'!D:D,"")} -> Brittney | C225: {=_xlfn.XLOOKUP(A225,'Video Database'!L:L,'Video Database'!E:E,"")} -> Account 4 | D225: {=_xlfn.XLOOKUP(A225,'Video Database'!L:L,'Video Database'!G:G,"")} -> Gruns Greens Popsicle Firecracker Gummies | E225: {=_xlfn.XLOOKUP(A225,'Video Database'!L:L,'Video Database'!H:H,"")} -> 1.1 | F225: 0 | G225: 0 | H225: {=_xlfn.XLOOKUP(A225,'Video Database'!L:L,'Video Database'!A:A,"")} -> 46186 | I225: 46201 | J225: 0 | L225: =M225 | O225: =iferror(K225/L225, NA()) -> #N/A | P225: =iferror(G225/K225, NA()) -> #N/A | Q225: =iferror(J225/G225,NA()) -> #N/A | R225: =iferror(F225/G225,NA()) -> #N/A | S225: =J225-E225 -> -1.1 | T225: =if(E225=0,"",S225/E225) -> -1 | U225: =iferror(S225/J225,na()) -> #N/A | V225: =if(G225=0,"",E225/G225) | W225: =if(K225=0,"",E225/K225) | X225: =if(F225=0,"",(E225/F225)*100) | Y225: {=_xlfn.XLOOKUP(A225,'Video Database'!L:L,'Video Database'!M:M,"")} -> Bottom of Funnel
A226: =A225+1 -> 225 | B226: {=_xlfn.XLOOKUP(A226,'Video Database'!L:L,'Video Database'!D:D,"")} -> Brittney | C226: {=_xlfn.XLOOKUP(A226,'Video Database'!L:L,'Video Database'!E:E,"")} -> Account 4 | D226: {=_xlfn.XLOOKUP(A226,'Video Database'!L:L,'Video Database'!G:G,"")} -> Gruns Greens Popsicle Firecracker Gummies | E226: {=_xlfn.XLOOKUP(A226,'Video Database'!L:L,'Video Database'!H:H,"")} -> 1.1 | F226: 0 | G226: 0 | H226: {=_xlfn.XLOOKUP(A226,'Video Database'!L:L,'Video Database'!A:A,"")} -> 46186 | I226: 46201 | J226: 0 | L226: =M226 | O226: =iferror(K226/L226, NA()) -> #N/A | P226: =iferror(G226/K226, NA()) -> #N/A | Q226: =iferror(J226/G226,NA()) -> #N/A | R226: =iferror(F226/G226,NA()) -> #N/A | S226: =J226-E226 -> -1.1 | T226: =if(E226=0,"",S226/E226) -> -1 | U226: =iferror(S226/J226,na()) -> #N/A | V226: =if(G226=0,"",E226/G226) | W226: =if(K226=0,"",E226/K226) | X226: =if(F226=0,"",(E226/F226)*100) | Y226: {=_xlfn.XLOOKUP(A226,'Video Database'!L:L,'Video Database'!M:M,"")} -> Bottom of Funnel
A227: =A226+1 -> 226 | B227: {=_xlfn.XLOOKUP(A227,'Video Database'!L:L,'Video Database'!D:D,"")} -> Brittney | C227: {=_xlfn.XLOOKUP(A227,'Video Database'!L:L,'Video Database'!E:E,"")} -> Account 4 | D227: {=_xlfn.XLOOKUP(A227,'Video Database'!L:L,'Video Database'!G:G,"")} -> Gruns Greens Popsicle Firecracker Gummies | E227: {=_xlfn.XLOOKUP(A227,'Video Database'!L:L,'Video Database'!H:H,"")} -> 1.1 | F227: 0 | G227: 0 | H227: {=_xlfn.XLOOKUP(A227,'Video Database'!L:L,'Video Database'!A:A,"")} -> 46186 | I227: 46201 | J227: 0 | L227: =M227 | O227: =iferror(K227/L227, NA()) -> #N/A | P227: =iferror(G227/K227, NA()) -> #N/A | Q227: =iferror(J227/G227,NA()) -> #N/A | R227: =iferror(F227/G227,NA()) -> #N/A | S227: =J227-E227 -> -1.1 | T227: =if(E227=0,"",S227/E227) -> -1 | U227: =iferror(S227/J227,na()) -> #N/A | V227: =if(G227=0,"",E227/G227) | W227: =if(K227=0,"",E227/K227) | X227: =if(F227=0,"",(E227/F227)*100) | Y227: {=_xlfn.XLOOKUP(A227,'Video Database'!L:L,'Video Database'!M:M,"")} -> Bottom of Funnel
A228: =A227+1 -> 227 | B228: {=_xlfn.XLOOKUP(A228,'Video Database'!L:L,'Video Database'!D:D,"")} -> Brittney | C228: {=_xlfn.XLOOKUP(A228,'Video Database'!L:L,'Video Database'!E:E,"")} -> Account 4 | D228: {=_xlfn.XLOOKUP(A228,'Video Database'!L:L,'Video Database'!G:G,"")} -> Gruns Greens Popsicle Firecracker Gummies | E228: {=_xlfn.XLOOKUP(A228,'Video Database'!L:L,'Video Database'!H:H,"")} -> 1.1 | F228: 0 | G228: 0 | H228: {=_xlfn.XLOOKUP(A228,'Video Database'!L:L,'Video Database'!A:A,"")} -> 46186 | I228: 46201 | J228: 0 | L228: =M228 | O228: =iferror(K228/L228, NA()) -> #N/A | P228: =iferror(G228/K228, NA()) -> #N/A | Q228: =iferror(J228/G228,NA()) -> #N/A | R228: =iferror(F228/G228,NA()) -> #N/A | S228: =J228-E228 -> -1.1 | T228: =if(E228=0,"",S228/E228) -> -1 | U228: =iferror(S228/J228,na()) -> #N/A | V228: =if(G228=0,"",E228/G228) | W228: =if(K228=0,"",E228/K228) | X228: =if(F228=0,"",(E228/F228)*100) | Y228: {=_xlfn.XLOOKUP(A228,'Video Database'!L:L,'Video Database'!M:M,"")} -> Bottom of Funnel
A229: =A228+1 -> 228 | B229: {=_xlfn.XLOOKUP(A229,'Video Database'!L:L,'Video Database'!D:D,"")} -> Brittney | C229: {=_xlfn.XLOOKUP(A229,'Video Database'!L:L,'Video Database'!E:E,"")} -> Account 4 | D229: {=_xlfn.XLOOKUP(A229,'Video Database'!L:L,'Video Database'!G:G,"")} -> Gruns Greens Popsicle Firecracker Gummies | E229: {=_xlfn.XLOOKUP(A229,'Video Database'!L:L,'Video Database'!H:H,"")} -> 1.1 | F229: 0 | G229: 0 | H229: {=_xlfn.XLOOKUP(A229,'Video Database'!L:L,'Video Database'!A:A,"")} -> 46186 | I229: 46201 | J229: 0 | L229: =M229 | O229: =iferror(K229/L229, NA()) -> #N/A | P229: =iferror(G229/K229, NA()) -> #N/A | Q229: =iferror(J229/G229,NA()) -> #N/A | R229: =iferror(F229/G229,NA()) -> #N/A | S229: =J229-E229 -> -1.1 | T229: =if(E229=0,"",S229/E229) -> -1 | U229: =iferror(S229/J229,na()) -> #N/A | V229: =if(G229=0,"",E229/G229) | W229: =if(K229=0,"",E229/K229) | X229: =if(F229=0,"",(E229/F229)*100) | Y229: {=_xlfn.XLOOKUP(A229,'Video Database'!L:L,'Video Database'!M:M,"")} -> Bottom of Funnel
A230: =A229+1 -> 229 | B230: {=_xlfn.XLOOKUP(A230,'Video Database'!L:L,'Video Database'!D:D,"")} -> Brittney | C230: {=_xlfn.XLOOKUP(A230,'Video Database'!L:L,'Video Database'!E:E,"")} -> Account 4 | D230: {=_xlfn.XLOOKUP(A230,'Video Database'!L:L,'Video Database'!G:G,"")} -> Gruns Greens Popsicle Firecracker Gummies | E230: {=_xlfn.XLOOKUP(A230,'Video Database'!L:L,'Video Database'!H:H,"")} -> 1.1 | F230: 0 | G230: 0 | H230: {=_xlfn.XLOOKUP(A230,'Video Database'!L:L,'Video Database'!A:A,"")} -> 46186 | I230: 46201 | J230: 0 | L230: =M230 | O230: =iferror(K230/L230, NA()) -> #N/A | P230: =iferror(G230/K230, NA()) -> #N/A | Q230: =iferror(J230/G230,NA()) -> #N/A | R230: =iferror(F230/G230,NA()) -> #N/A | S230: =J230-E230 -> -1.1 | T230: =if(E230=0,"",S230/E230) -> -1 | U230: =iferror(S230/J230,na()) -> #N/A | V230: =if(G230=0,"",E230/G230) | W230: =if(K230=0,"",E230/K230) | X230: =if(F230=0,"",(E230/F230)*100) | Y230: {=_xlfn.XLOOKUP(A230,'Video Database'!L:L,'Video Database'!M:M,"")} -> Bottom of Funnel
A231: =A230+1 -> 230 | B231: {=_xlfn.XLOOKUP(A231,'Video Database'!L:L,'Video Database'!D:D,"")} -> Brittney | C231: {=_xlfn.XLOOKUP(A231,'Video Database'!L:L,'Video Database'!E:E,"")} -> Account 4 | D231: {=_xlfn.XLOOKUP(A231,'Video Database'!L:L,'Video Database'!G:G,"")} -> Gruns Greens Popsicle Firecracker Gummies | E231: {=_xlfn.XLOOKUP(A231,'Video Database'!L:L,'Video Database'!H:H,"")} -> 1.1 | F231: 0 | G231: 0 | H231: {=_xlfn.XLOOKUP(A231,'Video Database'!L:L,'Video Database'!A:A,"")} -> 46186 | I231: 46201 | J231: 0 | L231: =M231 | O231: =iferror(K231/L231, NA()) -> #N/A | P231: =iferror(G231/K231, NA()) -> #N/A | Q231: =iferror(J231/G231,NA()) -> #N/A | R231: =iferror(F231/G231,NA()) -> #N/A | S231: =J231-E231 -> -1.1 | T231: =if(E231=0,"",S231/E231) -> -1 | U231: =iferror(S231/J231,na()) -> #N/A | V231: =if(G231=0,"",E231/G231) | W231: =if(K231=0,"",E231/K231) | X231: =if(F231=0,"",(E231/F231)*100) | Y231: {=_xlfn.XLOOKUP(A231,'Video Database'!L:L,'Video Database'!M:M,"")} -> Bottom of Funnel
A232: =A231+1 -> 231 | B232: {=_xlfn.XLOOKUP(A232,'Video Database'!L:L,'Video Database'!D:D,"")} -> Brittney | C232: {=_xlfn.XLOOKUP(A232,'Video Database'!L:L,'Video Database'!E:E,"")} -> Account 4 | D232: {=_xlfn.XLOOKUP(A232,'Video Database'!L:L,'Video Database'!G:G,"")} -> Gruns Greens Popsicle Firecracker Gummies | E232: {=_xlfn.XLOOKUP(A232,'Video Database'!L:L,'Video Database'!H:H,"")} -> 1.1 | F232: 0 | G232: 0 | H232: {=_xlfn.XLOOKUP(A232,'Video Database'!L:L,'Video Database'!A:A,"")} -> 46186 | I232: 46201 | J232: 0 | L232: =M232 | O232: =iferror(K232/L232, NA()) -> #N/A | P232: =iferror(G232/K232, NA()) -> #N/A | Q232: =iferror(J232/G232,NA()) -> #N/A | R232: =iferror(F232/G232,NA()) -> #N/A | S232: =J232-E232 -> -1.1 | T232: =if(E232=0,"",S232/E232) -> -1 | U232: =iferror(S232/J232,na()) -> #N/A | V232: =if(G232=0,"",E232/G232) | W232: =if(K232=0,"",E232/K232) | X232: =if(F232=0,"",(E232/F232)*100) | Y232: {=_xlfn.XLOOKUP(A232,'Video Database'!L:L,'Video Database'!M:M,"")} -> Bottom of Funnel
A233: =A232+1 -> 232 | B233: {=_xlfn.XLOOKUP(A233,'Video Database'!L:L,'Video Database'!D:D,"")} -> Brittney | C233: {=_xlfn.XLOOKUP(A233,'Video Database'!L:L,'Video Database'!E:E,"")} -> Account 4 | D233: {=_xlfn.XLOOKUP(A233,'Video Database'!L:L,'Video Database'!G:G,"")} -> Gruns Greens Popsicle Firecracker Gummies | E233: {=_xlfn.XLOOKUP(A233,'Video Database'!L:L,'Video Database'!H:H,"")} -> 1.1 | F233: 0 | G233: 0 | H233: {=_xlfn.XLOOKUP(A233,'Video Database'!L:L,'Video Database'!A:A,"")} -> 46186 | I233: 46201 | J233: 0 | L233: =M233 | O233: =iferror(K233/L233, NA()) -> #N/A | P233: =iferror(G233/K233, NA()) -> #N/A | Q233: =iferror(J233/G233,NA()) -> #N/A | R233: =iferror(F233/G233,NA()) -> #N/A | S233: =J233-E233 -> -1.1 | T233: =if(E233=0,"",S233/E233) -> -1 | U233: =iferror(S233/J233,na()) -> #N/A | V233: =if(G233=0,"",E233/G233) | W233: =if(K233=0,"",E233/K233) | X233: =if(F233=0,"",(E233/F233)*100) | Y233: {=_xlfn.XLOOKUP(A233,'Video Database'!L:L,'Video Database'!M:M,"")} -> Bottom of Funnel
A234: =A233+1 -> 233 | B234: {=_xlfn.XLOOKUP(A234,'Video Database'!L:L,'Video Database'!D:D,"")} -> Brittney | C234: {=_xlfn.XLOOKUP(A234,'Video Database'!L:L,'Video Database'!E:E,"")} -> Account 4 | D234: {=_xlfn.XLOOKUP(A234,'Video Database'!L:L,'Video Database'!G:G,"")} -> Gruns Greens Popsicle Firecracker Gummies | E234: {=_xlfn.XLOOKUP(A234,'Video Database'!L:L,'Video Database'!H:H,"")} -> 1.1 | F234: 0 | G234: 0 | H234: {=_xlfn.XLOOKUP(A234,'Video Database'!L:L,'Video Database'!A:A,"")} -> 46186 | I234: 46201 | J234: 0 | L234: =M234 | O234: =iferror(K234/L234, NA()) -> #N/A | P234: =iferror(G234/K234, NA()) -> #N/A | Q234: =iferror(J234/G234,NA()) -> #N/A | R234: =iferror(F234/G234,NA()) -> #N/A | S234: =J234-E234 -> -1.1 | T234: =if(E234=0,"",S234/E234) -> -1 | U234: =iferror(S234/J234,na()) -> #N/A | V234: =if(G234=0,"",E234/G234) | W234: =if(K234=0,"",E234/K234) | X234: =if(F234=0,"",(E234/F234)*100) | Y234: {=_xlfn.XLOOKUP(A234,'Video Database'!L:L,'Video Database'!M:M,"")} -> Bottom of Funnel
A235: =A234+1 -> 234 | B235: {=_xlfn.XLOOKUP(A235,'Video Database'!L:L,'Video Database'!D:D,"")} -> Brittney | C235: {=_xlfn.XLOOKUP(A235,'Video Database'!L:L,'Video Database'!E:E,"")} -> Account 4 | D235: {=_xlfn.XLOOKUP(A235,'Video Database'!L:L,'Video Database'!G:G,"")} -> Gruns Greens Popsicle Firecracker Gummies | E235: {=_xlfn.XLOOKUP(A235,'Video Database'!L:L,'Video Database'!H:H,"")} -> 1.1 | F235: 0 | G235: 0 | H235: {=_xlfn.XLOOKUP(A235,'Video Database'!L:L,'Video Database'!A:A,"")} -> 46186 | I235: 46201 | J235: 0 | L235: =M235 | O235: =iferror(K235/L235, NA()) -> #N/A | P235: =iferror(G235/K235, NA()) -> #N/A | Q235: =iferror(J235/G235,NA()) -> #N/A | R235: =iferror(F235/G235,NA()) -> #N/A | S235: =J235-E235 -> -1.1 | T235: =if(E235=0,"",S235/E235) -> -1 | U235: =iferror(S235/J235,na()) -> #N/A | V235: =if(G235=0,"",E235/G235) | W235: =if(K235=0,"",E235/K235) | X235: =if(F235=0,"",(E235/F235)*100) | Y235: {=_xlfn.XLOOKUP(A235,'Video Database'!L:L,'Video Database'!M:M,"")} -> Bottom of Funnel
... A299: =A298+1 -> 298 | B299: {=_xlfn.XLOOKUP(A299,'Video Database'!L:L,'Video Database'!D:D,"")} -> Blakely | C299: {=_xlfn.XLOOKUP(A299,'Video Database'!L:L,'Video Database'!E:E,"")} -> Account 2 | D299: {=_xlfn.XLOOKUP(A299,'Video Database'!L:L,'Video Database'!G:G,"")} -> Nello Supercalm Drink Mix | E299: {=_xlfn.XLOOKUP(A299,'Video Database'!L:L,'Video Database'!H:H,"")} -> 0.11 | F299: 0 | G299: 0 | H299: {=_xlfn.XLOOKUP(A299,'Video Database'!L:L,'Video Database'!A:A,"")} -> 46188 | I299: 46201 | J299: 0 | L299: =M299 | O299: =iferror(K299/L299, NA()) -> #N/A | P299: =iferror(G299/K299, NA()) -> #N/A | Q299: =iferror(J299/G299,NA()) -> #N/A | R299: =iferror(F299/G299,NA()) -> #N/A | S299: =J299-E299 -> -0.11 | T299: =if(E299=0,"",S299/E299) -> -1 | U299: =iferror(S299/J299,na()) -> #N/A | V299: =if(G299=0,"",E299/G299) | W299: =if(K299=0,"",E299/K299) | X299: =if(F299=0,"",(E299/F299)*100) | Y299: {=_xlfn.XLOOKUP(A299,'Video Database'!L:L,'Video Database'!M:M,"")} -> Bottom of Funnel
A300: =A299+1 -> 299 | B300: {=_xlfn.XLOOKUP(A300,'Video Database'!L:L,'Video Database'!D:D,"")} -> Blakely | C300: {=_xlfn.XLOOKUP(A300,'Video Database'!L:L,'Video Database'!E:E,"")} -> Account 2 | D300: {=_xlfn.XLOOKUP(A300,'Video Database'!L:L,'Video Database'!G:G,"")} -> Beast Bites Creatine Gummies | E300: {=_xlfn.XLOOKUP(A300,'Video Database'!L:L,'Video Database'!H:H,"")} -> 0.11 | F300: 0 | G300: 5 | H300: {=_xlfn.XLOOKUP(A300,'Video Database'!L:L,'Video Database'!A:A,"")} -> 46188 | I300: 46209 | J300: 11.84 | K300: 13 | L300: =M300 -> 88 | M300: 88 | O300: =iferror(K300/L300, NA()) -> 0.14772727 | P300: =iferror(G300/K300, NA()) -> 0.38461538 | Q300: =iferror(J300/G300,NA()) -> 2.368 | R300: =iferror(F300/G300,NA()) -> 0 | S300: =J300-E300 -> 11.73 | T300: =if(E300=0,"",S300/E300) -> 106.63636 | U300: =iferror(S300/J300,na()) -> 0.99070946 | V300: =if(G300=0,"",E300/G300) -> 0.022 | W300: =if(K300=0,"",E300/K300) -> 0.0084615385 | X300: =if(F300=0,"",(E300/F300)*100) | Y300: {=_xlfn.XLOOKUP(A300,'Video Database'!L:L,'Video Database'!M:M,"")} -> Bottom of Funnel
A301: =A300+1 -> 300 | B301: {=_xlfn.XLOOKUP(A301,'Video Database'!L:L,'Video Database'!D:D,"")} -> Blakely | C301: {=_xlfn.XLOOKUP(A301,'Video Database'!L:L,'Video Database'!E:E,"")} -> Account 2 | D301: {=_xlfn.XLOOKUP(A301,'Video Database'!L:L,'Video Database'!G:G,"")} -> Mushroom Coffee | E301: {=_xlfn.XLOOKUP(A301,'Video Database'!L:L,'Video Database'!H:H,"")} -> 0.11 | F301: 0 | G301: 0 | H301: {=_xlfn.XLOOKUP(A301,'Video Database'!L:L,'Video Database'!A:A,"")} -> 46188 | I301: 46201 | J301: 0 | L301: =M301 | O301: =iferror(K301/L301, NA()) -> #N/A | P301: =iferror(G301/K301, NA()) -> #N/A | Q301: =iferror(J301/G301,NA()) -> #N/A | R301: =iferror(F301/G301,NA()) -> #N/A | S301: =J301-E301 -> -0.11 | T301: =if(E301=0,"",S301/E301) -> -1 | U301: =iferror(S301/J301,na()) -> #N/A | V301: =if(G301=0,"",E301/G301) | W301: =if(K301=0,"",E301/K301) | X301: =if(F301=0,"",(E301/F301)*100) | Y301: {=_xlfn.XLOOKUP(A301,'Video Database'!L:L,'Video Database'!M:M,"")} -> Bottom of Funnel
A302: =A301+1 -> 301 | B302: {=_xlfn.XLOOKUP(A302,'Video Database'!L:L,'Video Database'!D:D,"")} -> Blakely | C302: {=_xlfn.XLOOKUP(A302,'Video Database'!L:L,'Video Database'!E:E,"")} -> Account 2 | D302: {=_xlfn.XLOOKUP(A302,'Video Database'!L:L,'Video Database'!G:G,"")} -> BioEmblem Magnesium | E302: {=_xlfn.XLOOKUP(A302,'Video Database'!L:L,'Video Database'!H:H,"")} -> 0.11 | F302: 0 | G302: 0 | H302: {=_xlfn.XLOOKUP(A302,'Video Database'!L:L,'Video Database'!A:A,"")} -> 46188 | I302: 46201 | J302: 0 | L302: =M302 | O302: =iferror(K302/L302, NA()) -> #N/A | P302: =iferror(G302/K302, NA()) -> #N/A | Q302: =iferror(J302/G302,NA()) -> #N/A | R302: =iferror(F302/G302,NA()) -> #N/A | S302: =J302-E302 -> -0.11 | T302: =if(E302=0,"",S302/E302) -> -1 | U302: =iferror(S302/J302,na()) -> #N/A | V302: =if(G302=0,"",E302/G302) | W302: =if(K302=0,"",E302/K302) | X302: =if(F302=0,"",(E302/F302)*100) | Y302: {=_xlfn.XLOOKUP(A302,'Video Database'!L:L,'Video Database'!M:M,"")} -> Bottom of Funnel
A303: =A302+1 -> 302 | B303: {=_xlfn.XLOOKUP(A303,'Video Database'!L:L,'Video Database'!D:D,"")} -> Blakely | C303: {=_xlfn.XLOOKUP(A303,'Video Database'!L:L,'Video Database'!E:E,"")} -> Account 2 | D303: {=_xlfn.XLOOKUP(A303,'Video Database'!L:L,'Video Database'!G:G,"")} -> Nutricost Creatine Monohydrate | E303: {=_xlfn.XLOOKUP(A303,'Video Database'!L:L,'Video Database'!H:H,"")} -> 0.11 | F303: 0 | G303: 0 | H303: {=_xlfn.XLOOKUP(A303,'Video Database'!L:L,'Video Database'!A:A,"")} -> 46188 | I303: 46201 | J303: 0 | L303: =M303 | O303: =iferror(K303/L303, NA()) -> #N/A | P303: =iferror(G303/K303, NA()) -> #N/A | Q303: =iferror(J303/G303,NA()) -> #N/A | R303: =iferror(F303/G303,NA()) -> #N/A | S303: =J303-E303 -> -0.11 | T303: =if(E303=0,"",S303/E303) -> -1 | U303: =iferror(S303/J303,na()) -> #N/A | V303: =if(G303=0,"",E303/G303) | W303: =if(K303=0,"",E303/K303) | X303: =if(F303=0,"",(E303/F303)*100) | Y303: {=_xlfn.XLOOKUP(A303,'Video Database'!L:L,'Video Database'!M:M,"")} -> Bottom of Funnel
A304: =A303+1 -> 303 | B304: {=_xlfn.XLOOKUP(A304,'Video Database'!L:L,'Video Database'!D:D,"")} -> Blakely | C304: {=_xlfn.XLOOKUP(A304,'Video Database'!L:L,'Video Database'!E:E,"")} -> Account 2 | D304: {=_xlfn.XLOOKUP(A304,'Video Database'!L:L,'Video Database'!G:G,"")} -> Goli Women's Complete Multi Gummy | E304: {=_xlfn.XLOOKUP(A304,'Video Database'!L:L,'Video Database'!H:H,"")} -> 0.11 | F304: 0 | G304: 0 | H304: {=_xlfn.XLOOKUP(A304,'Video Database'!L:L,'Video Database'!A:A,"")} -> 46188 | I304: 46201 | J304: 0 | L304: =M304 | O304: =iferror(K304/L304, NA()) -> #N/A | P304: =iferror(G304/K304, NA()) -> #N/A | Q304: =iferror(J304/G304,NA()) -> #N/A | R304: =iferror(F304/G304,NA()) -> #N/A | S304: =J304-E304 -> -0.11 | T304: =if(E304=0,"",S304/E304) -> -1 | U304: =iferror(S304/J304,na()) -> #N/A | V304: =if(G304=0,"",E304/G304) | W304: =if(K304=0,"",E304/K304) | X304: =if(F304=0,"",(E304/F304)*100) | Y304: {=_xlfn.XLOOKUP(A304,'Video Database'!L:L,'Video Database'!M:M,"")} -> Bottom of Funnel
A305: =A304+1 -> 304 | B305: {=_xlfn.XLOOKUP(A305,'Video Database'!L:L,'Video Database'!D:D,"")} -> Blakely | C305: {=_xlfn.XLOOKUP(A305,'Video Database'!L:L,'Video Database'!E:E,"")} -> Account 2 | D305: {=_xlfn.XLOOKUP(A305,'Video Database'!L:L,'Video Database'!G:G,"")} -> Physician's Choice Probiotic Gummies | E305: {=_xlfn.XLOOKUP(A305,'Video Database'!L:L,'Video Database'!H:H,"")} -> 0.11 | F305: 0 | G305: 0 | H305: {=_xlfn.XLOOKUP(A305,'Video Database'!L:L,'Video Database'!A:A,"")} -> 46188 | I305: 46201 | J305: 0 | L305: =M305 | O305: =iferror(K305/L305, NA()) -> #N/A | P305: =iferror(G305/K305, NA()) -> #N/A | Q305: =iferror(J305/G305,NA()) -> #N/A | R305: =iferror(F305/G305,NA()) -> #N/A | S305: =J305-E305 -> -0.11 | T305: =if(E305=0,"",S305/E305) -> -1 | U305: =iferror(S305/J305,na()) -> #N/A | V305: =if(G305=0,"",E305/G305) | W305: =if(K305=0,"",E305/K305) | X305: =if(F305=0,"",(E305/F305)*100) | Y305: {=_xlfn.XLOOKUP(A305,'Video Database'!L:L,'Video Database'!M:M,"")} -> Bottom of Funnel
A306: =A305+1 -> 305 | B306: {=_xlfn.XLOOKUP(A306,'Video Database'!L:L,'Video Database'!D:D,"")} -> Blakely | C306: {=_xlfn.XLOOKUP(A306,'Video Database'!L:L,'Video Database'!E:E,"")} -> Account 2 | D306: {=_xlfn.XLOOKUP(A306,'Video Database'!L:L,'Video Database'!G:G,"")} -> BetterAlt Shilajit Honey Sticks | E306: {=_xlfn.XLOOKUP(A306,'Video Database'!L:L,'Video Database'!H:H,"")} -> 0.11 | F306: 18.42 | G306: 1 | H306: {=_xlfn.XLOOKUP(A306,'Video Database'!L:L,'Video Database'!A:A,"")} -> 46188 | I306: 46201 | J306: 4.46 | K306: 4 | L306: =M306 -> 590 | M306: 590 | O306: =iferror(K306/L306, NA()) -> 0.006779661 | P306: =iferror(G306/K306, NA()) -> 0.25 | Q306: =iferror(J306/G306,NA()) -> 4.46 | R306: =iferror(F306/G306,NA()) -> 18.42 | S306: =J306-E306 -> 4.35 | T306: =if(E306=0,"",S306/E306) -> 39.545455 | U306: =iferror(S306/J306,na()) -> 0.97533632 | V306: =if(G306=0,"",E306/G306) -> 0.11 | W306: =if(K306=0,"",E306/K306) -> 0.0275 | X306: =if(F306=0,"",(E306/F306)*100) -> 0.59717698 | Y306: {=_xlfn.XLOOKUP(A306,'Video Database'!L:L,'Video Database'!M:M,"")} -> Bottom of Funnel
A307: =A306+1 -> 306 | B307: {=_xlfn.XLOOKUP(A307,'Video Database'!L:L,'Video Database'!D:D,"")} -> Blakely | C307: {=_xlfn.XLOOKUP(A307,'Video Database'!L:L,'Video Database'!E:E,"")} -> Account 2 | D307: {=_xlfn.XLOOKUP(A307,'Video Database'!L:L,'Video Database'!G:G,"")} -> Olov Electric Shaver | E307: {=_xlfn.XLOOKUP(A307,'Video Database'!L:L,'Video Database'!H:H,"")} -> 0.11 | F307: 0 | G307: 0 | H307: {=_xlfn.XLOOKUP(A307,'Video Database'!L:L,'Video Database'!A:A,"")} -> 46188 | I307: 46201 | J307: 0 | L307: =M307 | O307: =iferror(K307/L307, NA()) -> #N/A | P307: =iferror(G307/K307, NA()) -> #N/A | Q307: =iferror(J307/G307,NA()) -> #N/A | R307: =iferror(F307/G307,NA()) -> #N/A | S307: =J307-E307 -> -0.11 | T307: =if(E307=0,"",S307/E307) -> -1 | U307: =iferror(S307/J307,na()) -> #N/A | V307: =if(G307=0,"",E307/G307) | W307: =if(K307=0,"",E307/K307) | X307: =if(F307=0,"",(E307/F307)*100) | Y307: {=_xlfn.XLOOKUP(A307,'Video Database'!L:L,'Video Database'!M:M,"")} -> Bottom of Funnel
A308: =A307+1 -> 307 | B308: {=_xlfn.XLOOKUP(A308,'Video Database'!L:L,'Video Database'!D:D,"")} -> Blakely | C308: {=_xlfn.XLOOKUP(A308,'Video Database'!L:L,'Video Database'!E:E,"")} -> Account 2 | D308: {=_xlfn.XLOOKUP(A308,'Video Database'!L:L,'Video Database'!G:G,"")} -> Neurogum Watermelon | E308: {=_xlfn.XLOOKUP(A308,'Video Database'!L:L,'Video Database'!H:H,"")} -> 0.11 | F308: 0 | G308: 0 | H308: {=_xlfn.XLOOKUP(A308,'Video Database'!L:L,'Video Database'!A:A,"")} -> 46188 | I308: 46201 | J308: 0 | L308: =M308 | O308: =iferror(K308/L308, NA()) -> #N/A | P308: =iferror(G308/K308, NA()) -> #N/A | Q308: =iferror(J308/G308,NA()) -> #N/A | R308: =iferror(F308/G308,NA()) -> #N/A | S308: =J308-E308 -> -0.11 | T308: =if(E308=0,"",S308/E308) -> -1 | U308: =iferror(S308/J308,na()) -> #N/A | V308: =if(G308=0,"",E308/G308) | W308: =if(K308=0,"",E308/K308) | X308: =if(F308=0,"",(E308/F308)*100) | Y308: {=_xlfn.XLOOKUP(A308,'Video Database'!L:L,'Video Database'!M:M,"")} -> Bottom of Funnel
A309: =A308+1 -> 308 | B309: {=_xlfn.XLOOKUP(A309,'Video Database'!L:L,'Video Database'!D:D,"")} -> Blakely | C309: {=_xlfn.XLOOKUP(A309,'Video Database'!L:L,'Video Database'!E:E,"")} -> Account 2 | D309: {=_xlfn.XLOOKUP(A309,'Video Database'!L:L,'Video Database'!G:G,"")} -> Squish Energy Preworkout Jello Shots | E309: {=_xlfn.XLOOKUP(A309,'Video Database'!L:L,'Video Database'!H:H,"")} -> 0.11 | F309: 0 | G309: 0 | H309: {=_xlfn.XLOOKUP(A309,'Video Database'!L:L,'Video Database'!A:A,"")} -> 46188 | I309: 46201 | J309: 0 | L309: =M309 | O309: =iferror(K309/L309, NA()) -> #N/A | P309: =iferror(G309/K309, NA()) -> #N/A | Q309: =iferror(J309/G309,NA()) -> #N/A | R309: =iferror(F309/G309,NA()) -> #N/A | S309: =J309-E309 -> -0.11 | T309: =if(E309=0,"",S309/E309) -> -1 | U309: =iferror(S309/J309,na()) -> #N/A | V309: =if(G309=0,"",E309/G309) | W309: =if(K309=0,"",E309/K309) | X309: =if(F309=0,"",(E309/F309)*100) | Y309: {=_xlfn.XLOOKUP(A309,'Video Database'!L:L,'Video Database'!M:M,"")} -> Bottom of Funnel
A310: =A309+1 -> 309 | B310: {=_xlfn.XLOOKUP(A310,'Video Database'!L:L,'Video Database'!D:D,"")} -> Blakely | C310: {=_xlfn.XLOOKUP(A310,'Video Database'!L:L,'Video Database'!E:E,"")} -> Account 2 | D310: {=_xlfn.XLOOKUP(A310,'Video Database'!L:L,'Video Database'!G:G,"")} -> BetterAlt Shilajit Honey Sticks | E310: {=_xlfn.XLOOKUP(A310,'Video Database'!L:L,'Video Database'!H:H,"")} -> 0.11 | F310: 0 | G310: 0 | H310: {=_xlfn.XLOOKUP(A310,'Video Database'!L:L,'Video Database'!A:A,"")} -> 46188 | I310: 46201 | J310: 0 | L310: =M310 | O310: =iferror(K310/L310, NA()) -> #N/A | P310: =iferror(G310/K310, NA()) -> #N/A | Q310: =iferror(J310/G310,NA()) -> #N/A | R310: =iferror(F310/G310,NA()) -> #N/A | S310: =J310-E310 -> -0.11 | T310: =if(E310=0,"",S310/E310) -> -1 | U310: =iferror(S310/J310,na()) -> #N/A | V310: =if(G310=0,"",E310/G310) | W310: =if(K310=0,"",E310/K310) | X310: =if(F310=0,"",(E310/F310)*100) | Y310: {=_xlfn.XLOOKUP(A310,'Video Database'!L:L,'Video Database'!M:M,"")} -> Bottom of Funnel
A311: =A310+1 -> 310 | B311: {=_xlfn.XLOOKUP(A311,'Video Database'!L:L,'Video Database'!D:D,"")} -> Blakely | C311: {=_xlfn.XLOOKUP(A311,'Video Database'!L:L,'Video Database'!E:E,"")} -> Account 2 | D311: {=_xlfn.XLOOKUP(A311,'Video Database'!L:L,'Video Database'!G:G,"")} -> BioEmblem Magnesium | E311: {=_xlfn.XLOOKUP(A311,'Video Database'!L:L,'Video Database'!H:H,"")} -> 0.11 | F311: 0 | G311: 0 | H311: {=_xlfn.XLOOKUP(A311,'Video Database'!L:L,'Video Database'!A:A,"")} -> 46188 | I311: 46201 | J311: 0 | L311: =M311 | O311: =iferror(K311/L311, NA()) -> #N/A | P311: =iferror(G311/K311, NA()) -> #N/A | Q311: =iferror(J311/G311,NA()) -> #N/A | R311: =iferror(F311/G311,NA()) -> #N/A | S311: =J311-E311 -> -0.11 | T311: =if(E311=0,"",S311/E311) -> -1 | U311: =iferror(S311/J311,na()) -> #N/A | V311: =if(G311=0,"",E311/G311) | W311: =if(K311=0,"",E311/K311) | X311: =if(F311=0,"",(E311/F311)*100) | Y311: {=_xlfn.XLOOKUP(A311,'Video Database'!L:L,'Video Database'!M:M,"")} -> Bottom of Funnel
A312: =A311+1 -> 311 | B312: {=_xlfn.XLOOKUP(A312,'Video Database'!L:L,'Video Database'!D:D,"")} -> Blakely | C312: {=_xlfn.XLOOKUP(A312,'Video Database'!L:L,'Video Database'!E:E,"")} -> Account 2 | D312: {=_xlfn.XLOOKUP(A312,'Video Database'!L:L,'Video Database'!G:G,"")} -> Nutricost Creatine Monohydrate | E312: {=_xlfn.XLOOKUP(A312,'Video Database'!L:L,'Video Database'!H:H,"")} -> 0.11 | F312: 0 | G312: 0 | H312: {=_xlfn.XLOOKUP(A312,'Video Database'!L:L,'Video Database'!A:A,"")} -> 46188 | I312: 46201 | J312: 0 | L312: =M312 | O312: =iferror(K312/L312, NA()) -> #N/A | P312: =iferror(G312/K312, NA()) -> #N/A | Q312: =iferror(J312/G312,NA()) -> #N/A | R312: =iferror(F312/G312,NA()) -> #N/A | S312: =J312-E312 -> -0.11 | T312: =if(E312=0,"",S312/E312) -> -1 | U312: =iferror(S312/J312,na()) -> #N/A | V312: =if(G312=0,"",E312/G312) | W312: =if(K312=0,"",E312/K312) | X312: =if(F312=0,"",(E312/F312)*100) | Y312: {=_xlfn.XLOOKUP(A312,'Video Database'!L:L,'Video Database'!M:M,"")} -> Bottom of Funnel
A313: =A312+1 -> 312 | B313: {=_xlfn.XLOOKUP(A313,'Video Database'!L:L,'Video Database'!D:D,"")} -> Blakely | C313: {=_xlfn.XLOOKUP(A313,'Video Database'!L:L,'Video Database'!E:E,"")} -> Account 2 | D313: {=_xlfn.XLOOKUP(A313,'Video Database'!L:L,'Video Database'!G:G,"")} -> Beast Bites Creatine Gummies | E313: {=_xlfn.XLOOKUP(A313,'Video Database'!L:L,'Video Database'!H:H,"")} -> 0.11 | F313: 0 | G313: 0 | H313: {=_xlfn.XLOOKUP(A313,'Video Database'!L:L,'Video Database'!A:A,"")} -> 46188 | I313: 46201 | J313: 0 | L313: =M313 | O313: =iferror(K313/L313, NA()) -> #N/A | P313: =iferror(G313/K313, NA()) -> #N/A | Q313: =iferror(J313/G313,NA()) -> #N/A | R313: =iferror(F313/G313,NA()) -> #N/A | S313: =J313-E313 -> -0.11 | T313: =if(E313=0,"",S313/E313) -> -1 | U313: =iferror(S313/J313,na()) -> #N/A | V313: =if(G313=0,"",E313/G313) | W313: =if(K313=0,"",E313/K313) | X313: =if(F313=0,"",(E313/F313)*100) | Y313: {=_xlfn.XLOOKUP(A313,'Video Database'!L:L,'Video Database'!M:M,"")} -> Bottom of Funnel
A314: =A313+1 -> 313 | B314: {=_xlfn.XLOOKUP(A314,'Video Database'!L:L,'Video Database'!D:D,"")} -> Blakely | C314: {=_xlfn.XLOOKUP(A314,'Video Database'!L:L,'Video Database'!E:E,"")} -> Account 2 | D314: {=_xlfn.XLOOKUP(A314,'Video Database'!L:L,'Video Database'!G:G,"")} -> Nello Supercalm Drink Mix | E314: {=_xlfn.XLOOKUP(A314,'Video Database'!L:L,'Video Database'!H:H,"")} -> 0.11 | F314: 0 | G314: 0 | H314: {=_xlfn.XLOOKUP(A314,'Video Database'!L:L,'Video Database'!A:A,"")} -> 46188 | I314: 46201 | J314: 0 | L314: =M314 | O314: =iferror(K314/L314, NA()) -> #N/A | P314: =iferror(G314/K314, NA()) -> #N/A | Q314: =iferror(J314/G314,NA()) -> #N/A | R314: =iferror(F314/G314,NA()) -> #N/A | S314: =J314-E314 -> -0.11 | T314: =if(E314=0,"",S314/E314) -> -1 | U314: =iferror(S314/J314,na()) -> #N/A | V314: =if(G314=0,"",E314/G314) | W314: =if(K314=0,"",E314/K314) | X314: =if(F314=0,"",(E314/F314)*100) | Y314: {=_xlfn.XLOOKUP(A314,'Video Database'!L:L,'Video Database'!M:M,"")} -> Bottom of Funnel
A315: =A314+1 -> 314 | B315: {=_xlfn.XLOOKUP(A315,'Video Database'!L:L,'Video Database'!D:D,"")} -> Blakely | C315: {=_xlfn.XLOOKUP(A315,'Video Database'!L:L,'Video Database'!E:E,"")} -> Account 2 | D315: {=_xlfn.XLOOKUP(A315,'Video Database'!L:L,'Video Database'!G:G,"")} -> Neurogum Watermelon | E315: {=_xlfn.XLOOKUP(A315,'Video Database'!L:L,'Video Database'!H:H,"")} -> 0.11 | F315: 0 | G315: 0 | H315: {=_xlfn.XLOOKUP(A315,'Video Database'!L:L,'Video Database'!A:A,"")} -> 46188 | I315: 46201 | J315: 0 | L315: =M315 | O315: =iferror(K315/L315, NA()) -> #N/A | P315: =iferror(G315/K315, NA()) -> #N/A | Q315: =iferror(J315/G315,NA()) -> #N/A | R315: =iferror(F315/G315,NA()) -> #N/A | S315: =J315-E315 -> -0.11 | T315: =if(E315=0,"",S315/E315) -> -1 | U315: =iferror(S315/J315,na()) -> #N/A | V315: =if(G315=0,"",E315/G315) | W315: =if(K315=0,"",E315/K315) | X315: =if(F315=0,"",(E315/F315)*100) | Y315: {=_xlfn.XLOOKUP(A315,'Video Database'!L:L,'Video Database'!M:M,"")} -> Bottom of Funnel
A316: =A315+1 -> 315 | B316: {=_xlfn.XLOOKUP(A316,'Video Database'!L:L,'Video Database'!D:D,"")} -> Blakely | C316: {=_xlfn.XLOOKUP(A316,'Video Database'!L:L,'Video Database'!E:E,"")} -> Account 2 | D316: {=_xlfn.XLOOKUP(A316,'Video Database'!L:L,'Video Database'!G:G,"")} -> Goli Women's Complete Multi Gummy | E316: {=_xlfn.XLOOKUP(A316,'Video Database'!L:L,'Video Database'!H:H,"")} -> 0.11 | F316: 0 | G316: 0 | H316: {=_xlfn.XLOOKUP(A316,'Video Database'!L:L,'Video Database'!A:A,"")} -> 46188 | I316: 46201 | J316: 0 | L316: =M316 | O316: =iferror(K316/L316, NA()) -> #N/A | P316: =iferror(G316/K316, NA()) -> #N/A | Q316: =iferror(J316/G316,NA()) -> #N/A | R316: =iferror(F316/G316,NA()) -> #N/A | S316: =J316-E316 -> -0.11 | T316: =if(E316=0,"",S316/E316) -> -1 | U316: =iferror(S316/J316,na()) -> #N/A | V316: =if(G316=0,"",E316/G316) | W316: =if(K316=0,"",E316/K316) | X316: =if(F316=0,"",(E316/F316)*100) | Y316: {=_xlfn.XLOOKUP(A316,'Video Database'!L:L,'Video Database'!M:M,"")} -> Bottom of Funnel
A317: =A316+1 -> 316 | B317: {=_xlfn.XLOOKUP(A317,'Video Database'!L:L,'Video Database'!D:D,"")} -> Blakely | C317: {=_xlfn.XLOOKUP(A317,'Video Database'!L:L,'Video Database'!E:E,"")} -> Account 2 | D317: {=_xlfn.XLOOKUP(A317,'Video Database'!L:L,'Video Database'!G:G,"")} -> Physician's Choice Probiotic Gummies | E317: {=_xlfn.XLOOKUP(A317,'Video Database'!L:L,'Video Database'!H:H,"")} -> 0.11 | F317: 0 | G317: 0 | H317: {=_xlfn.XLOOKUP(A317,'Video Database'!L:L,'Video Database'!A:A,"")} -> 46188 | I317: 46201 | J317: 0 | L317: =M317 | O317: =iferror(K317/L317, NA()) -> #N/A | P317: =iferror(G317/K317, NA()) -> #N/A | Q317: =iferror(J317/G317,NA()) -> #N/A | R317: =iferror(F317/G317,NA()) -> #N/A | S317: =J317-E317 -> -0.11 | T317: =if(E317=0,"",S317/E317) -> -1 | U317: =iferror(S317/J317,na()) -> #N/A | V317: =if(G317=0,"",E317/G317) | W317: =if(K317=0,"",E317/K317) | X317: =if(F317=0,"",(E317/F317)*100) | Y317: {=_xlfn.XLOOKUP(A317,'Video Database'!L:L,'Video Database'!M:M,"")} -> Bottom of Funnel
A318: =A317+1 -> 317 | B318: {=_xlfn.XLOOKUP(A318,'Video Database'!L:L,'Video Database'!D:D,"")} -> Blakely | C318: {=_xlfn.XLOOKUP(A318,'Video Database'!L:L,'Video Database'!E:E,"")} -> Account 2 | D318: {=_xlfn.XLOOKUP(A318,'Video Database'!L:L,'Video Database'!G:G,"")} -> Mushroom Coffee | E318: {=_xlfn.XLOOKUP(A318,'Video Database'!L:L,'Video Database'!H:H,"")} -> 0.11 | F318: 0 | G318: 0 | H318: {=_xlfn.XLOOKUP(A318,'Video Database'!L:L,'Video Database'!A:A,"")} -> 46188 | I318: 46201 | J318: 0 | L318: =M318 | O318: =iferror(K318/L318, NA()) -> #N/A | P318: =iferror(G318/K318, NA()) -> #N/A | Q318: =iferror(J318/G318,NA()) -> #N/A | R318: =iferror(F318/G318,NA()) -> #N/A | S318: =J318-E318 -> -0.11 | T318: =if(E318=0,"",S318/E318) -> -1 | U318: =iferror(S318/J318,na()) -> #N/A | V318: =if(G318=0,"",E318/G318) | W318: =if(K318=0,"",E318/K318) | X318: =if(F318=0,"",(E318/F318)*100) | Y318: {=_xlfn.XLOOKUP(A318,'Video Database'!L:L,'Video Database'!M:M,"")} -> Bottom of Funnel
... A322: =A321+1 -> 321 | B322: {=_xlfn.XLOOKUP(A322,'Video Database'!L:L,'Video Database'!D:D,"")} -> Blakely | C322: {=_xlfn.XLOOKUP(A322,'Video Database'!L:L,'Video Database'!E:E,"")} -> Account 3 | D322: {=_xlfn.XLOOKUP(A322,'Video Database'!L:L,'Video Database'!G:G,"")} -> Nello Supercalm Drink Mix | E322: {=_xlfn.XLOOKUP(A322,'Video Database'!L:L,'Video Database'!H:H,"")} -> 0.11 | F322: 0 | G322: 0 | H322: {=_xlfn.XLOOKUP(A322,'Video Database'!L:L,'Video Database'!A:A,"")} -> 46188 | I322: 46201 | J322: 0 | L322: =M322 | O322: =iferror(K322/L322, NA()) -> #N/A | P322: =iferror(G322/K322, NA()) -> #N/A | Q322: =iferror(J322/G322,NA()) -> #N/A | R322: =iferror(F322/G322,NA()) -> #N/A | S322: =J322-E322 -> -0.11 | T322: =if(E322=0,"",S322/E322) -> -1 | U322: =iferror(S322/J322,na()) -> #N/A | V322: =if(G322=0,"",E322/G322) | W322: =if(K322=0,"",E322/K322) | X322: =if(F322=0,"",(E322/F322)*100) | Y322: {=_xlfn.XLOOKUP(A322,'Video Database'!L:L,'Video Database'!M:M,"")} -> Bottom of Funnel
A323: =A322+1 -> 322 | B323: {=_xlfn.XLOOKUP(A323,'Video Database'!L:L,'Video Database'!D:D,"")} -> Blakely | C323: {=_xlfn.XLOOKUP(A323,'Video Database'!L:L,'Video Database'!E:E,"")} -> Account 3 | D323: {=_xlfn.XLOOKUP(A323,'Video Database'!L:L,'Video Database'!G:G,"")} -> Beast Bites Creatine Gummies | E323: {=_xlfn.XLOOKUP(A323,'Video Database'!L:L,'Video Database'!H:H,"")} -> 0.11 | F323: 14.21 | G323: 1 | H323: {=_xlfn.XLOOKUP(A323,'Video Database'!L:L,'Video Database'!A:A,"")} -> 46188 | I323: 46201 | J323: 1.58 | K323: 3 | L323: =M323 -> 1400 | M323: 1400 | O323: =iferror(K323/L323, NA()) -> 0.0021428571 | P323: =iferror(G323/K323, NA()) -> 0.33333333 | Q323: =iferror(J323/G323,NA()) -> 1.58 | R323: =iferror(F323/G323,NA()) -> 14.21 | S323: =J323-E323 -> 1.47 | T323: =if(E323=0,"",S323/E323) -> 13.363636 | U323: =iferror(S323/J323,na()) -> 0.93037975 | V323: =if(G323=0,"",E323/G323) -> 0.11 | W323: =if(K323=0,"",E323/K323) -> 0.036666667 | X323: =if(F323=0,"",(E323/F323)*100) -> 0.77410274 | Y323: {=_xlfn.XLOOKUP(A323,'Video Database'!L:L,'Video Database'!M:M,"")} -> Bottom of Funnel
A324: =A323+1 -> 323 | B324: {=_xlfn.XLOOKUP(A324,'Video Database'!L:L,'Video Database'!D:D,"")} -> Blakely | C324: {=_xlfn.XLOOKUP(A324,'Video Database'!L:L,'Video Database'!E:E,"")} -> Account 3 | D324: {=_xlfn.XLOOKUP(A324,'Video Database'!L:L,'Video Database'!G:G,"")} -> Goli Women's Complete Multi Gummy | E324: {=_xlfn.XLOOKUP(A324,'Video Database'!L:L,'Video Database'!H:H,"")} -> 0.11 | F324: 0 | G324: 0 | H324: {=_xlfn.XLOOKUP(A324,'Video Database'!L:L,'Video Database'!A:A,"")} -> 46188 | I324: 46201 | J324: 0 | L324: =M324 | O324: =iferror(K324/L324, NA()) -> #N/A | P324: =iferror(G324/K324, NA()) -> #N/A | Q324: =iferror(J324/G324,NA()) -> #N/A | R324: =iferror(F324/G324,NA()) -> #N/A | S324: =J324-E324 -> -0.11 | T324: =if(E324=0,"",S324/E324) -> -1 | U324: =iferror(S324/J324,na()) -> #N/A | V324: =if(G324=0,"",E324/G324) | W324: =if(K324=0,"",E324/K324) | X324: =if(F324=0,"",(E324/F324)*100) | Y324: {=_xlfn.XLOOKUP(A324,'Video Database'!L:L,'Video Database'!M:M,"")} -> Bottom of Funnel
A325: =A324+1 -> 324 | B325: {=_xlfn.XLOOKUP(A325,'Video Database'!L:L,'Video Database'!D:D,"")} -> Blakely | C325: {=_xlfn.XLOOKUP(A325,'Video Database'!L:L,'Video Database'!E:E,"")} -> Account 3 | D325: {=_xlfn.XLOOKUP(A325,'Video Database'!L:L,'Video Database'!G:G,"")} -> Physician's Choice Probiotic Gummies | E325: {=_xlfn.XLOOKUP(A325,'Video Database'!L:L,'Video Database'!H:H,"")} -> 0.11 | F325: 0 | G325: 0 | H325: {=_xlfn.XLOOKUP(A325,'Video Database'!L:L,'Video Database'!A:A,"")} -> 46188 | I325: 46201 | J325: 0 | L325: =M325 | O325: =iferror(K325/L325, NA()) -> #N/A | P325: =iferror(G325/K325, NA()) -> #N/A | Q325: =iferror(J325/G325,NA()) -> #N/A | R325: =iferror(F325/G325,NA()) -> #N/A | S325: =J325-E325 -> -0.11 | T325: =if(E325=0,"",S325/E325) -> -1 | U325: =iferror(S325/J325,na()) -> #N/A | V325: =if(G325=0,"",E325/G325) | W325: =if(K325=0,"",E325/K325) | X325: =if(F325=0,"",(E325/F325)*100) | Y325: {=_xlfn.XLOOKUP(A325,'Video Database'!L:L,'Video Database'!M:M,"")} -> Bottom of Funnel
A326: =A325+1 -> 325 | B326: {=_xlfn.XLOOKUP(A326,'Video Database'!L:L,'Video Database'!D:D,"")} -> Blakely | C326: {=_xlfn.XLOOKUP(A326,'Video Database'!L:L,'Video Database'!E:E,"")} -> Account 3 | D326: {=_xlfn.XLOOKUP(A326,'Video Database'!L:L,'Video Database'!G:G,"")} -> Nutricost Creatine Monohydrate | E326: {=_xlfn.XLOOKUP(A326,'Video Database'!L:L,'Video Database'!H:H,"")} -> 0.11 | F326: 0 | G326: 0 | H326: {=_xlfn.XLOOKUP(A326,'Video Database'!L:L,'Video Database'!A:A,"")} -> 46188 | I326: 46201 | J326: 0 | L326: =M326 | O326: =iferror(K326/L326, NA()) -> #N/A | P326: =iferror(G326/K326, NA()) -> #N/A | Q326: =iferror(J326/G326,NA()) -> #N/A | R326: =iferror(F326/G326,NA()) -> #N/A | S326: =J326-E326 -> -0.11 | T326: =if(E326=0,"",S326/E326) -> -1 | U326: =iferror(S326/J326,na()) -> #N/A | V326: =if(G326=0,"",E326/G326) | W326: =if(K326=0,"",E326/K326) | X326: =if(F326=0,"",(E326/F326)*100) | Y326: {=_xlfn.XLOOKUP(A326,'Video Database'!L:L,'Video Database'!M:M,"")} -> Bottom of Funnel
A327: =A326+1 -> 326 | B327: {=_xlfn.XLOOKUP(A327,'Video Database'!L:L,'Video Database'!D:D,"")} -> Blakely | C327: {=_xlfn.XLOOKUP(A327,'Video Database'!L:L,'Video Database'!E:E,"")} -> Account 3 | D327: {=_xlfn.XLOOKUP(A327,'Video Database'!L:L,'Video Database'!G:G,"")} -> BetterAlt Shilajit Honey Sticks | E327: {=_xlfn.XLOOKUP(A327,'Video Database'!L:L,'Video Database'!H:H,"")} -> 0.11 | F327: 0 | G327: 0 | H327: {=_xlfn.XLOOKUP(A327,'Video Database'!L:L,'Video Database'!A:A,"")} -> 46188 | I327: 46201 | J327: 0 | L327: =M327 | O327: =iferror(K327/L327, NA()) -> #N/A | P327: =iferror(G327/K327, NA()) -> #N/A | Q327: =iferror(J327/G327,NA()) -> #N/A | R327: =iferror(F327/G327,NA()) -> #N/A | S327: =J327-E327 -> -0.11 | T327: =if(E327=0,"",S327/E327) -> -1 | U327: =iferror(S327/J327,na()) -> #N/A | V327: =if(G327=0,"",E327/G327) | W327: =if(K327=0,"",E327/K327) | X327: =if(F327=0,"",(E327/F327)*100) | Y327: {=_xlfn.XLOOKUP(A327,'Video Database'!L:L,'Video Database'!M:M,"")} -> Bottom of Funnel
A328: =A327+1 -> 327 | B328: {=_xlfn.XLOOKUP(A328,'Video Database'!L:L,'Video Database'!D:D,"")} -> Blakely | C328: {=_xlfn.XLOOKUP(A328,'Video Database'!L:L,'Video Database'!E:E,"")} -> Account 3 | D328: {=_xlfn.XLOOKUP(A328,'Video Database'!L:L,'Video Database'!G:G,"")} -> BioEmblem Magnesium | E328: {=_xlfn.XLOOKUP(A328,'Video Database'!L:L,'Video Database'!H:H,"")} -> 0.11 | F328: 0 | G328: 0 | H328: {=_xlfn.XLOOKUP(A328,'Video Database'!L:L,'Video Database'!A:A,"")} -> 46188 | I328: 46201 | J328: 0 | L328: =M328 | O328: =iferror(K328/L328, NA()) -> #N/A | P328: =iferror(G328/K328, NA()) -> #N/A | Q328: =iferror(J328/G328,NA()) -> #N/A | R328: =iferror(F328/G328,NA()) -> #N/A | S328: =J328-E328 -> -0.11 | T328: =if(E328=0,"",S328/E328) -> -1 | U328: =iferror(S328/J328,na()) -> #N/A | V328: =if(G328=0,"",E328/G328) | W328: =if(K328=0,"",E328/K328) | X328: =if(F328=0,"",(E328/F328)*100) | Y328: {=_xlfn.XLOOKUP(A328,'Video Database'!L:L,'Video Database'!M:M,"")} -> Bottom of Funnel
A329: =A328+1 -> 328 | B329: {=_xlfn.XLOOKUP(A329,'Video Database'!L:L,'Video Database'!D:D,"")} -> Blakely | C329: {=_xlfn.XLOOKUP(A329,'Video Database'!L:L,'Video Database'!E:E,"")} -> Account 3 | D329: {=_xlfn.XLOOKUP(A329,'Video Database'!L:L,'Video Database'!G:G,"")} -> Olov Electric Shaver | E329: {=_xlfn.XLOOKUP(A329,'Video Database'!L:L,'Video Database'!H:H,"")} -> 0.11 | F329: 0 | G329: 0 | H329: {=_xlfn.XLOOKUP(A329,'Video Database'!L:L,'Video Database'!A:A,"")} -> 46188 | I329: 46201 | J329: 0 | L329: =M329 | O329: =iferror(K329/L329, NA()) -> #N/A | P329: =iferror(G329/K329, NA()) -> #N/A | Q329: =iferror(J329/G329,NA()) -> #N/A | R329: =iferror(F329/G329,NA()) -> #N/A | S329: =J329-E329 -> -0.11 | T329: =if(E329=0,"",S329/E329) -> -1 | U329: =iferror(S329/J329,na()) -> #N/A | V329: =if(G329=0,"",E329/G329) | W329: =if(K329=0,"",E329/K329) | X329: =if(F329=0,"",(E329/F329)*100) | Y329: {=_xlfn.XLOOKUP(A329,'Video Database'!L:L,'Video Database'!M:M,"")} -> Bottom of Funnel
A330: =A329+1 -> 329 | B330: {=_xlfn.XLOOKUP(A330,'Video Database'!L:L,'Video Database'!D:D,"")} -> Blakely | C330: {=_xlfn.XLOOKUP(A330,'Video Database'!L:L,'Video Database'!E:E,"")} -> Account 3 | D330: {=_xlfn.XLOOKUP(A330,'Video Database'!L:L,'Video Database'!G:G,"")} -> Neurogum Watermelon | E330: {=_xlfn.XLOOKUP(A330,'Video Database'!L:L,'Video Database'!H:H,"")} -> 0.11 | F330: 0 | G330: 0 | H330: {=_xlfn.XLOOKUP(A330,'Video Database'!L:L,'Video Database'!A:A,"")} -> 46188 | I330: 46201 | J330: 0 | L330: =M330 | O330: =iferror(K330/L330, NA()) -> #N/A | P330: =iferror(G330/K330, NA()) -> #N/A | Q330: =iferror(J330/G330,NA()) -> #N/A | R330: =iferror(F330/G330,NA()) -> #N/A | S330: =J330-E330 -> -0.11 | T330: =if(E330=0,"",S330/E330) -> -1 | U330: =iferror(S330/J330,na()) -> #N/A | V330: =if(G330=0,"",E330/G330) | W330: =if(K330=0,"",E330/K330) | X330: =if(F330=0,"",(E330/F330)*100) | Y330: {=_xlfn.XLOOKUP(A330,'Video Database'!L:L,'Video Database'!M:M,"")} -> Bottom of Funnel
...

Sheet Pivot Tables
G1: Video # | H1: Creator | I1: Account | J1: Product | K1: Orders | L1: Commission | M1: Profit | N1: ROI | V1: ROI | W1: Cost per Order | X1: Commission Per Video | Y1: Profit Per Video
G2: =IFERROR(__xludf.DUMMYFUNCTION("ARRAY_CONSTRAIN( CHOOSECOLS( SORT( FILTER( 'Performance Data'!A2:X2235, 'Performance Data'!A2:A2235<>"""", 'Performance Data'!B2:B2235<>"""" ), 19, FALSE ), 1,2,3,4,7,10,19,20 ), 10, 8 )"),1146.0) -> 1146 | H2: =IFERROR(__xludf.DUMMYFUNCTION("""COMPUTED_VALUE"""),"Sierra") -> Sierra | I2: =IFERROR(__xludf.DUMMYFUNCTION("""COMPUTED_VALUE"""),"Account 4") -> Account 4 | J2: =IFERROR(__xludf.DUMMYFUNCTION("""COMPUTED_VALUE"""),"Taste Salud Skin + Beauty Drink Mix") -> Taste Salud Skin + Beauty Drink Mix | K2: =IFERROR(__xludf.DUMMYFUNCTION("""COMPUTED_VALUE"""),2.0) -> 2 | L2: =IFERROR(__xludf.DUMMYFUNCTION("""COMPUTED_VALUE"""),14.57) -> 14.57 | M2: =IFERROR(__xludf.DUMMYFUNCTION("""COMPUTED_VALUE"""),13.47) -> 13.47 | N2: =IFERROR(__xludf.DUMMYFUNCTION("""COMPUTED_VALUE"""),12.245454545454544) -> 12.245455 | V2: =if(S2=0,"",T2/S2) -> 0.70309478 | W2: =if(U2=0,"",S2/U2) -> 1.6832558 | X2: =if(Q2=0,"",R2/Q2) -> 0.18734043 | Y2: =if(Q2=0,"",T2/Q2) -> 0.077340426
G3: =IFERROR(__xludf.DUMMYFUNCTION("""COMPUTED_VALUE"""),901.0) -> 901 | H3: =IFERROR(__xludf.DUMMYFUNCTION("""COMPUTED_VALUE"""),"Blakely") -> Blakely | I3: =IFERROR(__xludf.DUMMYFUNCTION("""COMPUTED_VALUE"""),"Account 4") -> Account 4 | J3: =IFERROR(__xludf.DUMMYFUNCTION("""COMPUTED_VALUE"""),"JOYMODE Ignite Libido Support") -> JOYMODE Ignite Libido Support | K3: =IFERROR(__xludf.DUMMYFUNCTION("""COMPUTED_VALUE"""),4.0) -> 4 | L3: =IFERROR(__xludf.DUMMYFUNCTION("""COMPUTED_VALUE"""),13.2) -> 13.2 | M3: =IFERROR(__xludf.DUMMYFUNCTION("""COMPUTED_VALUE"""),13.09) -> 13.09 | N3: =IFERROR(__xludf.DUMMYFUNCTION("""COMPUTED_VALUE"""),119.0) -> 119 | V3: =if(S3=0,"",T3/S3) -> -0.91880706 | W3: =if(U3=0,"",S3/U3) -> 41.85093 | X3: =if(Q3=0,"",R3/Q3) -> 0.066237817 | Y3: =if(Q3=0,"",T3/Q3) -> -0.74956979
G4: =IFERROR(__xludf.DUMMYFUNCTION("""COMPUTED_VALUE"""),299.0) -> 299 | H4: =IFERROR(__xludf.DUMMYFUNCTION("""COMPUTED_VALUE"""),"Blakely") -> Blakely | I4: =IFERROR(__xludf.DUMMYFUNCTION("""COMPUTED_VALUE"""),"Account 2") -> Account 2 | J4: =IFERROR(__xludf.DUMMYFUNCTION("""COMPUTED_VALUE"""),"Beast Bites Creatine Gummies") -> Beast Bites Creatine Gummies | K4: =IFERROR(__xludf.DUMMYFUNCTION("""COMPUTED_VALUE"""),5.0) -> 5 | L4: =IFERROR(__xludf.DUMMYFUNCTION("""COMPUTED_VALUE"""),11.84) -> 11.84 | M4: =IFERROR(__xludf.DUMMYFUNCTION("""COMPUTED_VALUE"""),11.73) -> 11.73 | N4: =IFERROR(__xludf.DUMMYFUNCTION("""COMPUTED_VALUE"""),106.63636363636364) -> 106.63636 | V4: =if(S4=0,"",T4/S4) -> -0.68643579 | W4: =if(U4=0,"",S4/U4) -> 17.325 | X4: =if(Q4=0,"",R4/Q4) -> 0.34492063 | Y4: =if(Q4=0,"",T4/Q4) -> -0.75507937
G5: =IFERROR(__xludf.DUMMYFUNCTION("""COMPUTED_VALUE"""),634.0) -> 634 | H5: =IFERROR(__xludf.DUMMYFUNCTION("""COMPUTED_VALUE"""),"Blakely") -> Blakely | I5: =IFERROR(__xludf.DUMMYFUNCTION("""COMPUTED_VALUE"""),"Account 2") -> Account 2 | J5: =IFERROR(__xludf.DUMMYFUNCTION("""COMPUTED_VALUE"""),"JOYMODE Ignite Libido Support") -> JOYMODE Ignite Libido Support | K5: =IFERROR(__xludf.DUMMYFUNCTION("""COMPUTED_VALUE"""),2.0) -> 2 | L5: =IFERROR(__xludf.DUMMYFUNCTION("""COMPUTED_VALUE"""),8.8) -> 8.8 | M5: =IFERROR(__xludf.DUMMYFUNCTION("""COMPUTED_VALUE"""),8.690000000000001) -> 8.69 | N5: =IFERROR(__xludf.DUMMYFUNCTION("""COMPUTED_VALUE"""),79.00000000000001) -> 79 | V5: =if(S5=0,"",T5/S5) -> -0.50651629 | W5: =if(U5=0,"",S5/U5) -> 3.99 | X5: =if(Q5=0,"",R5/Q5) -> 0.16789922 | Y5: =if(Q5=0,"",T5/Q5) -> -0.17233333
G6: =IFERROR(__xludf.DUMMYFUNCTION("""COMPUTED_VALUE"""),734.0) -> 734 | H6: =IFERROR(__xludf.DUMMYFUNCTION("""COMPUTED_VALUE"""),"Brittney") -> Brittney | I6: =IFERROR(__xludf.DUMMYFUNCTION("""COMPUTED_VALUE"""),"Account 4") -> Account 4 | J6: =IFERROR(__xludf.DUMMYFUNCTION("""COMPUTED_VALUE"""),"Gruns Greens Popsicle Firecracker Gummies") -> Gruns Greens Popsicle Firecracker Gummies | K6: =IFERROR(__xludf.DUMMYFUNCTION("""COMPUTED_VALUE"""),4.0) -> 4 | L6: =IFERROR(__xludf.DUMMYFUNCTION("""COMPUTED_VALUE"""),8.59) -> 8.59 | M6: =IFERROR(__xludf.DUMMYFUNCTION("""COMPUTED_VALUE"""),8.48) -> 8.48 | N6: =IFERROR(__xludf.DUMMYFUNCTION("""COMPUTED_VALUE"""),77.0909090909091) -> 77.090909 | V6: =if(S6=0,"",T6/S6) -> -1 | W6: =if(U6=0,"",S6/U6) | X6: =if(Q6=0,"",R6/Q6) -> 0 | Y6: =if(Q6=0,"",T6/Q6) -> -1.1
G7: =IFERROR(__xludf.DUMMYFUNCTION("""COMPUTED_VALUE"""),1013.0) -> 1013 | H7: =IFERROR(__xludf.DUMMYFUNCTION("""COMPUTED_VALUE"""),"Blakely") -> Blakely | I7: =IFERROR(__xludf.DUMMYFUNCTION("""COMPUTED_VALUE"""),"Account 3") -> Account 3 | J7: =IFERROR(__xludf.DUMMYFUNCTION("""COMPUTED_VALUE"""),"tarte CC Color-Correct Tinted Serum") -> tarte CC Color-Correct Tinted Serum | K7: =IFERROR(__xludf.DUMMYFUNCTION("""COMPUTED_VALUE"""),1.0) -> 1 | L7: =IFERROR(__xludf.DUMMYFUNCTION("""COMPUTED_VALUE"""),7.2) -> 7.2 | M7: =IFERROR(__xludf.DUMMYFUNCTION("""COMPUTED_VALUE"""),7.09) -> 7.09 | N7: =IFERROR(__xludf.DUMMYFUNCTION("""COMPUTED_VALUE"""),64.45454545454545) -> 64.454545 | V7: =if(S7=0,"",T7/S7) -> -1 | W7: =if(U7=0,"",S7/U7) | X7: =if(Q7=0,"",R7/Q7) -> 0 | Y7: =if(Q7=0,"",T7/Q7) -> -1.1
G8: =IFERROR(__xludf.DUMMYFUNCTION("""COMPUTED_VALUE"""),725.0) -> 725 | H8: =IFERROR(__xludf.DUMMYFUNCTION("""COMPUTED_VALUE"""),"Blakely") -> Blakely | I8: =IFERROR(__xludf.DUMMYFUNCTION("""COMPUTED_VALUE"""),"Account 3") -> Account 3 | J8: =IFERROR(__xludf.DUMMYFUNCTION("""COMPUTED_VALUE"""),"Swanson Full Spectrum Spearmint Leaf") -> Swanson Full Spectrum Spearmint Leaf | K8: =IFERROR(__xludf.DUMMYFUNCTION("""COMPUTED_VALUE"""),1.0) -> 1 | L8: =IFERROR(__xludf.DUMMYFUNCTION("""COMPUTED_VALUE"""),7.12) -> 7.12 | M8: =IFERROR(__xludf.DUMMYFUNCTION("""COMPUTED_VALUE"""),7.01) -> 7.01 | N8: =IFERROR(__xludf.DUMMYFUNCTION("""COMPUTED_VALUE"""),63.72727272727273) -> 63.727273
G9: =IFERROR(__xludf.DUMMYFUNCTION("""COMPUTED_VALUE"""),1065.0) -> 1065 | H9: =IFERROR(__xludf.DUMMYFUNCTION("""COMPUTED_VALUE"""),"Blakely") -> Blakely | I9: =IFERROR(__xludf.DUMMYFUNCTION("""COMPUTED_VALUE"""),"Account 4") -> Account 4 | J9: =IFERROR(__xludf.DUMMYFUNCTION("""COMPUTED_VALUE"""),"IRIS Hormone Health Drink Mix") -> IRIS Hormone Health Drink Mix | K9: =IFERROR(__xludf.DUMMYFUNCTION("""COMPUTED_VALUE"""),2.0) -> 2 | L9: =IFERROR(__xludf.DUMMYFUNCTION("""COMPUTED_VALUE"""),5.93) -> 5.93 | M9: =IFERROR(__xludf.DUMMYFUNCTION("""COMPUTED_VALUE"""),5.819999999999999) -> 5.82 | N9: =IFERROR(__xludf.DUMMYFUNCTION("""COMPUTED_VALUE"""),52.90909090909091) -> 52.909091
G10: =IFERROR(__xludf.DUMMYFUNCTION("""COMPUTED_VALUE"""),1348.0) -> 1348 | H10: =IFERROR(__xludf.DUMMYFUNCTION("""COMPUTED_VALUE"""),"Sierra") -> Sierra | I10: =IFERROR(__xludf.DUMMYFUNCTION("""COMPUTED_VALUE"""),"Account 4") -> Account 4 | J10: =IFERROR(__xludf.DUMMYFUNCTION("""COMPUTED_VALUE"""),"Taste Salud Skin + Beauty Drink Mix") -> Taste Salud Skin + Beauty Drink Mix | K10: =IFERROR(__xludf.DUMMYFUNCTION("""COMPUTED_VALUE"""),1.0) -> 1 | L10: =IFERROR(__xludf.DUMMYFUNCTION("""COMPUTED_VALUE"""),5.76) -> 5.76 | M10: =IFERROR(__xludf.DUMMYFUNCTION("""COMPUTED_VALUE"""),4.66) -> 4.66 | N10: =IFERROR(__xludf.DUMMYFUNCTION("""COMPUTED_VALUE"""),4.236363636363636) -> 4.2363636 | Z10: ROI
G11: =IFERROR(__xludf.DUMMYFUNCTION("""COMPUTED_VALUE"""),451.0) -> 451 | H11: =IFERROR(__xludf.DUMMYFUNCTION("""COMPUTED_VALUE"""),"Blakely") -> Blakely | I11: =IFERROR(__xludf.DUMMYFUNCTION("""COMPUTED_VALUE"""),"Account 3") -> Account 3 | J11: =IFERROR(__xludf.DUMMYFUNCTION("""COMPUTED_VALUE"""),"Cutler Nutrition Liquid Carnitine 3000") -> Cutler Nutrition Liquid Carnitine 3000 | K11: =IFERROR(__xludf.DUMMYFUNCTION("""COMPUTED_VALUE"""),1.0) -> 1 | L11: =IFERROR(__xludf.DUMMYFUNCTION("""COMPUTED_VALUE"""),4.5) -> 4.5 | M11: =IFERROR(__xludf.DUMMYFUNCTION("""COMPUTED_VALUE"""),4.39) -> 4.39 | N11: =IFERROR(__xludf.DUMMYFUNCTION("""COMPUTED_VALUE"""),39.90909090909091) -> 39.909091 | Z11: =if(X11=0,"",X11/W11) -> -0.58239696
Z12: =if(X12=0,"",X12/W12) -> -0.83591228
Z13: =if(X13=0,"",X13/W13) -> -0.74902162
N14: ROI | O14: Profit Per Video | P14: Cost per Order | Q14: Commission Per Video | R14: Videos per Order | Z14: =if(X14=0,"",X14/W14) -> -0.66256006
N15: =if(L15=0,"",M15/L15) -> 14.897727 | O15: =if(H15=0,"",M15/H15) -> 1.63875 | P15: =if(I15=0,"",L15/I15) -> 0.19555556 | Q15: =if(H15=0,"",K15/H15) -> 1.74875 | R15: =if(I15=0,"",H15/I15) -> 1.7777778
N16: =if(L16=0,"",M16/L16) -> 4.8651026 | O16: =if(H16=0,"",M16/H16) -> 0.53516129 | P16: =if(I16=0,"",L16/I16) -> 0.56833333 | Q16: =if(H16=0,"",K16/H16) -> 0.64516129 | R16: =if(I16=0,"",H16/I16) -> 5.1666667
N17: =if(L17=0,"",M17/L17) -> 2.1422925 | O17: =if(H17=0,"",M17/H17) -> 0.23565217 | P17: =if(I17=0,"",L17/I17) -> 1.012 | Q17: =if(H17=0,"",K17/H17) -> 0.34565217 | R17: =if(I17=0,"",H17/I17) -> 9.2 | T17: Content Style | U17: Videos | V17: Commission | W17: Cost | X17: Profit | Y17: Orders | Z17: ROI
N18: =if(L18=0,"",M18/L18) -> 2.2727273 | O18: =if(H18=0,"",M18/H18) -> 0.25 | P18: =if(I18=0,"",L18/I18) -> 1.4666667 | Q18: =if(H18=0,"",K18/H18) -> 0.36 | R18: =if(I18=0,"",H18/I18) -> 13.333333 | T18: Bottom of Funnel | U18: 833 | V18: 77.75 | W18: 485.3893 | X18: -407.6393 | Y18: 27 | Z18: =if(X18=0,"",X18/W18) -> -0.8398193
N19: =if(L19=0,"",M19/L19) -> 1.5957447 | O19: =if(H19=0,"",M19/H19) -> 0.17553191 | P19: =if(I19=0,"",L19/I19) -> 0.86166667 | Q19: =if(H19=0,"",K19/H19) -> 0.28553191 | R19: =if(I19=0,"",H19/I19) -> 7.8333333 | T19: Middle of Funnel | U19: 144 | V19: 21.73 | W19: 104.94 | X19: -83.21 | Y19: 4 | Z19: =if(X19=0,"",X19/W19) -> -0.79292929
N20: =if(L20=0,"",M20/L20) -> 7.0909091 | O20: =if(H20=0,"",M20/H20) -> 0.78 | P20: =if(I20=0,"",L20/I20) -> 0.88 | Q20: =if(H20=0,"",K20/H20) -> 0.89 | R20: =if(I20=0,"",H20/I20) -> 8 | T20: Product Overlay | U20: 415 | V20: 101.159 | W20: 45.65 | X20: 55.509 | Y20: 37 | Z20: =if(X20=0,"",X20/W20) -> 1.2159693
N21: =if(L21=0,"",M21/L21) -> 7.1818182 | O21: =if(H21=0,"",M21/H21) -> 0.79 | P21: =if(I21=0,"",L21/I21) -> 0.55 | Q21: =if(H21=0,"",K21/H21) -> 0.9 | R21: =if(I21=0,"",H21/I21) -> 5
N22: =if(L22=0,"",M22/L22) -> 2.9848485 | O22: =if(H22=0,"",M22/H22) -> 0.32833333 | P22: =if(I22=0,"",L22/I22) -> 0.33 | Q22: =if(H22=0,"",K22/H22) -> 0.43833333 | R22: =if(I22=0,"",H22/I22) -> 3
N23: =if(L23=0,"",M23/L23) -> 3.0909091 | O23: =if(H23=0,"",M23/H23) -> 0.34 | P23: =if(I23=0,"",L23/I23) -> 0.88 | Q23: =if(H23=0,"",K23/H23) -> 0.45 | R23: =if(I23=0,"",H23/I23) -> 8
N24: =if(L24=0,"",M24/L24) -> 0.81818182 | O24: =if(H24=0,"",M24/H24) -> 0.09 | P24: =if(I24=0,"",L24/I24) -> 0.55 | Q24: =if(H24=0,"",K24/H24) -> 0.2 | R24: =if(I24=0,"",H24/I24) -> 5
N25: =if(L25=0,"",M25/L25) -> 0.18181818 | O25: =if(H25=0,"",M25/H25) -> 0.02 | P25: =if(I25=0,"",L25/I25) -> 0.88 | Q25: =if(H25=0,"",K25/H25) -> 0.13 | R25: =if(I25=0,"",H25/I25) -> 8
N26: =if(L26=0,"",M26/L26) -> -0.18660287 | O26: =if(H26=0,"",M26/H26) -> -0.020526316 | P26: =if(I26=0,"",L26/I26) -> 2.09 | Q26: =if(H26=0,"",K26/H26) -> 0.089473684 | R26: =if(I26=0,"",H26/I26) -> 19
N27: =if(L27=0,"",M27/L27) -> -1 | O27: =if(H27=0,"",M27/H27) -> -0.11 | P27: =if(I27=0,"",L27/I27) | Q27: =if(H27=0,"",K27/H27) -> 0 | R27: =if(I27=0,"",H27/I27)
N28: =if(L28=0,"",M28/L28) -> -1 | O28: =if(H28=0,"",M28/H28) -> -0.11 | P28: =if(I28=0,"",L28/I28) | Q28: =if(H28=0,"",K28/H28) -> 0 | R28: =if(I28=0,"",H28/I28)
N29: =if(L29=0,"",M29/L29) -> -1 | O29: =if(H29=0,"",M29/H29) -> -0.11 | P29: =if(I29=0,"",L29/I29) | Q29: =if(H29=0,"",K29/H29) -> 0 | R29: =if(I29=0,"",H29/I29)
N30: =if(L30=0,"",M30/L30) -> -1 | O30: =if(H30=0,"",M30/H30) -> -0.11 | P30: =if(I30=0,"",L30/I30) | Q30: =if(H30=0,"",K30/H30) -> 0 | R30: =if(I30=0,"",H30/I30)
N31: =if(L31=0,"",M31/L31) -> -1 | O31: =if(H31=0,"",M31/H31) -> -0.11 | P31: =if(I31=0,"",L31/I31) | Q31: =if(H31=0,"",K31/H31) -> 0 | R31: =if(I31=0,"",H31/I31)
N32: =if(L32=0,"",M32/L32) -> -1 | O32: =if(H32=0,"",M32/H32) -> -0.11 | P32: =if(I32=0,"",L32/I32) | Q32: =if(H32=0,"",K32/H32) -> 0 | R32: =if(I32=0,"",H32/I32)
... N75: =if(L75=0,"",M75/L75) -> -1 | O75: =if(H75=0,"",M75/H75) -> -0.8813 | P75: =if(I75=0,"",L75/I75) | Q75: =if(H75=0,"",K75/H75) -> 0 | R75: =if(I75=0,"",H75/I75)
